{"day": "20260612", "results": {"005930": {"naver": true, "eps": "ok", "bps": "ok", "per": "ok", "pbr": "ok"}, "000660": {"naver": true, "eps": "ok", "bps": "ok", "per": "ok", "pbr": "ok"}, "402340": {"naver": true, "eps": "ok", "bps": "ok", "per": "ok", "pbr": "ok"}, "009150": {"naver": true, "eps": "ok", "bps": "ok", "per": "ok", "pbr": "ok"}, "005380": {"naver": true, "eps": "ok", "bps": "ok", "per": "ok", "pbr": "ok"}, "373220": {"naver": true, "eps": "mismatch(-1920 vs -6851.0)", "bps": "ok", "per": "ok_unverified", "pbr": "ok"}, "032830": {"naver": true, "eps": "ok", "bps": "ok", "per": "ok", "pbr": "ok"}, "028260": {"naver": true, "eps": "ok", "bps": "ok", "per": "ok", "pbr": "ok"}, "329180": {"naver": true, "eps": "mismatch(18150 vs 20237.0)", "bps": "ok", "per": "mismatch(35.81 vs 32.12)", "pbr": "ok"}, "000270": {"naver": true, "eps": "ok", "bps": "ok", "per": "ok", "pbr": "ok"}, "207940": {"naver": true, "eps": "mismatch(40570 vs 30779.0)", "bps": "ok", "per": "mismatch(31.92 vs 42.07)", "pbr": "ok"}, "034020": {"naver": true, "eps": "mismatch(166 vs 241.0)", "bps": "ok", "per": "mismatch(560.84 vs 386.31)", "pbr": "ok"}, "105560": {"naver": true, "eps": "ok", "bps": "ok", "per": "ok", "pbr": "ok"}, "012450": {"naver": true, "eps": "ok", "bps": "ok", "per": "ok", "pbr": "ok"}, "012330": {"naver": true, "eps": "ok", "bps": "ok", "per": "ok", "pbr": "ok"}, "055550": {"naver": true, "eps": "ok", "bps": "ok", "per": "ok", "pbr": "ok"}, "006400": {"naver": true, "eps": "mismatch(-4830 vs -5686.0)", "bps": "ok", "per": "ok_unverified", "pbr": "ok"}, "034730": {"naver": true, "eps": "ok", "bps": "ok", "per": "ok", "pbr": "ok"}, "267260": {"naver": true, "eps": "ok", "bps": "ok", "per": "ok", "pbr": "ok"}, "035420": {"naver": true, "eps": "ok", "bps": "ok", "per": "ok", "pbr": "ok"}, "068270": {"naver": true, "eps": "mismatch(5717 vs 5226.0)", "bps": "ok", "per": "mismatch(30.26 vs 33.1)", "pbr": "ok"}, "066570": {"naver": true, "eps": "mismatch(5999 vs 5420.0)", "bps": "mismatch(156982 vs 142232.0)", "per": "mismatch(37.59 vs 41.61)", "pbr": "mismatch(1.44 vs 1.59)"}, "042660": {"naver": true, "eps": "ok", "bps": "ok", "per": "ok", "pbr": "ok"}, "042700": {"naver": true, "eps": "ok", "bps": "ok", "per": "ok", "pbr": "ok"}, "010120": {"naver": true, "eps": "mismatch(11325 vs 2248.0)", "bps": "mismatch(69538 vs 13908.0)", "per": "mismatch(19.65 vs 98.98)", "pbr": "mismatch(3.2 vs 16.0)"}, "086790": {"naver": true, "eps": "ok", "bps": "ok", "per": "ok", "pbr": "ok"}, "298040": {"naver": true, "eps": "ok", "bps": "ok", "per": "ok", "pbr": "ok"}, "000150": {"naver": true, "eps": "mismatch(6398 vs 4286.0)", "bps": "mismatch(136276 vs 123409.0)", "per": "mismatch(296.34 vs 442.37)", "pbr": "mismatch(13.91 vs 15.36)"}, "005490": {"naver": true, "eps": "mismatch(8269 vs 10164.0)", "bps": "ok", "per": "mismatch(45.59 vs 37.09)", "pbr": "ok"}, "006800": {"naver": true, "eps": "mismatch(4122 vs 3187.0)", "bps": "ok", "per": "mismatch(12.69 vs 16.41)", "pbr": "ok"}, "000810": {"naver": true, "eps": "ok", "bps": "mismatch(567996 vs 500071.0)", "per": "ok", "pbr": "mismatch(1.15 vs 1.31)"}, "009540": {"naver": true, "eps": "ok", "bps": "ok", "per": "ok", "pbr": "ok"}, "010130": {"naver": true, "eps": "ok", "bps": "ok", "per": "ok", "pbr": "ok"}, "011070": {"naver": true, "eps": "ok", "bps": "ok", "per": "ok", "pbr": "ok"}, "051910": {"naver": true, "eps": "mismatch(-15555 vs -26317.0)", "bps": "ok", "per": "ok_unverified", "pbr": "ok"}, "015760": {"naver": true, "eps": "ok", "bps": "ok", "per": "ok", "pbr": "ok"}, "010140": {"naver": true, "eps": "ok", "bps": "ok", "per": "ok", "pbr": "ok"}, "316140": {"naver": true, "eps": "ok", "bps": "ok", "per": "ok", "pbr": "ok"}, "064350": {"naver": true, "eps": "ok", "bps": "ok", "per": "ok", "pbr": "ok"}, "017670": {"naver": true, "eps": "mismatch(1550 vs 1706.0)", "bps": "ok", "per": "mismatch(66.45 vs 60.38)", "pbr": "ok"}, "033780": {"naver": true, "eps": "ok", "bps": "ok", "per": "ok", "pbr": "ok"}, "267250": {"naver": true, "eps": "ok", "bps": "ok", "per": "ok", "pbr": "ok"}, "011200": {"naver": true, "eps": "ok", "bps": "ok", "per": "ok", "pbr": "ok"}, "307950": {"naver": true, "eps": "ok", "bps": "ok", "per": "ok", "pbr": "ok"}, "018260": {"naver": true, "eps": "ok", "bps": "ok", "per": "ok", "pbr": "ok"}, "035720": {"naver": true, "eps": "ok", "bps": "ok", "per": "ok", "pbr": "ok"}, "138040": {"naver": true, "eps": "ok", "bps": "ok", "per": "ok", "pbr": "ok"}, "272210": {"naver": true, "eps": "mismatch(615 vs 844.0)", "bps": "ok", "per": "mismatch(156.1 vs 113.74)", "pbr": "ok"}, "196170": {"naver": true, "eps": "blank", "bps": "ok", "per": "blank", "pbr": "ok"}, "096770": {"naver": true, "eps": "ok", "bps": "ok", "per": "ok_unverified", "pbr": "ok"}, "003670": {"naver": true, "eps": "ok", "bps": "ok", "per": "ok_unverified", "pbr": "ok"}, "000720": {"naver": true, "eps": "ok", "bps": "ok", "per": "ok", "pbr": "ok"}, "024110": {"naver": true, "eps": "ok", "bps": "ok", "per": "ok", "pbr": "ok"}, "079550": {"naver": true, "eps": "ok", "bps": "ok", "per": "ok", "pbr": "ok"}, "247540": {"naver": true, "eps": "ok", "bps": "ok", "per": "ok", "pbr": "ok"}, "003550": {"naver": true, "eps": "ok", "bps": "ok", "per": "ok", "pbr": "ok"}, "086520": {"naver": true, "eps": "mismatch(777 vs 452.0)", "bps": "ok", "per": "mismatch(148.91 vs 255.97)", "pbr": "ok"}, "086280": {"naver": true, "eps": "ok", "bps": "ok", "per": "ok", "pbr": "ok"}, "278470": {"naver": true, "eps": "ok", "bps": "ok", "per": "ok", "pbr": "ok"}, "030200": {"naver": true, "eps": "ok", "bps": "ok", "per": "ok", "pbr": "ok"}, "047810": {"naver": true, "eps": "ok", "bps": "ok", "per": "ok", "pbr": "ok"}, "071050": {"naver": true, "eps": "mismatch(44447 vs 40219.0)", "bps": "ok", "per": "mismatch(5.41 vs 5.98)", "pbr": "ok"}, "010950": {"naver": true, "eps": "blank", "bps": "ok", "per": "blank", "pbr": "ok"}, "277810": {"naver": true, "eps": "ok", "bps": "ok", "per": "ok", "pbr": "ok"}, "006260": {"naver": true, "eps": "ok", "bps": "ok", "per": "ok", "pbr": "ok"}, "323410": {"naver": true, "eps": "ok", "bps": "ok", "per": "ok", "pbr": "ok"}, "005940": {"naver": true, "eps": "ok", "bps": "ok", "per": "ok", "pbr": "ok"}, "0126Z0": {"naver": true, "eps": "blank", "bps": "blank", "per": "blank", "pbr": "blank"}, "443060": {"naver": true, "eps": "ok", "bps": "ok", "per": "ok", "pbr": "ok"}, "259960": {"naver": true, "eps": "ok", "bps": "ok", "per": "ok", "pbr": "ok"}, "036930": {"naver": true, "eps": "ok", "bps": "ok", "per": "ok", "pbr": "ok"}, "016360": {"naver": true, "eps": "ok", "bps": "ok", "per": "ok", "pbr": "ok"}, "047050": {"naver": true, "eps": "ok", "bps": "ok", "per": "ok", "pbr": "ok"}, "003490": {"naver": true, "eps": "mismatch(1072 vs 1670.0)", "bps": "mismatch(35803 vs 29417.0)", "per": "mismatch(24.81 vs 15.93)", "pbr": "mismatch(0.74 vs 0.9)"}, "005830": {"naver": true, "eps": "ok", "bps": "ok", "per": "ok", "pbr": "ok"}, "352820": {"naver": true, "eps": "ok", "bps": "ok", "per": "ok_unverified", "pbr": "ok"}, "039490": {"naver": true, "eps": "ok", "bps": "ok", "per": "ok", "pbr": "ok"}, "028050": {"naver": true, "eps": "ok", "bps": "ok", "per": "ok", "pbr": "ok"}, "240810": {"naver": true, "eps": "ok", "bps": "ok", "per": "ok", "pbr": "ok"}, "064400": {"naver": true, "eps": "ok", "bps": "ok", "per": "ok", "pbr": "ok"}, "007660": {"naver": true, "eps": "ok", "bps": "ok", "per": "ok", "pbr": "ok"}, "047040": {"naver": true, "eps": "ok", "bps": "ok", "per": "ok_unverified", "pbr": "ok"}, "161390": {"naver": true, "eps": "mismatch(8117 vs 9009.0)", "bps": "ok", "per": "mismatch(8.87 vs 7.99)", "pbr": "ok"}, "950160": {"naver": true, "eps": "blank", "bps": "blank", "per": "no_naver", "pbr": "blank"}, "003230": {"naver": true, "eps": "ok", "bps": "ok", "per": "ok", "pbr": "ok"}, "000880": {"naver": true, "eps": "mismatch(6120 vs 4618.0)", "bps": "mismatch(175039 vs 138948.0)", "per": "mismatch(19.0 vs 25.18)", "pbr": "mismatch(0.66 vs 0.84)"}, "353200": {"naver": true, "eps": "ok", "bps": "ok", "per": "ok", "pbr": "ok"}, "180640": {"naver": true, "eps": "ok", "bps": "ok", "per": "ok", "pbr": "ok"}, "058470": {"naver": true, "eps": "ok", "bps": "ok", "per": "ok", "pbr": "ok"}, "000990": {"naver": true, "eps": "ok", "bps": "ok", "per": "ok", "pbr": "ok"}, "039030": {"naver": true, "eps": "ok", "bps": "ok", "per": "ok", "pbr": "ok"}, "001440": {"naver": true, "eps": "ok", "bps": "mismatch(9252 vs 8522.0)", "per": "ok", "pbr": "ok"}, "454910": {"naver": true, "eps": "ok", "bps": "ok", "per": "ok_unverified", "pbr": "ok"}, "062040": {"naver": true, "eps": "blank", "bps": "ok", "per": "blank", "pbr": "ok"}, "011790": {"naver": true, "eps": "ok", "bps": "mismatch(22048 vs 24508.0)", "per": "ok_unverified", "pbr": "mismatch(6.36 vs 5.72)"}, "034220": {"naver": true, "eps": "mismatch(-214 vs -163.0)", "bps": "ok", "per": "ok_unverified", "pbr": "ok"}, "326030": {"naver": true, "eps": "ok", "bps": "ok", "per": "ok", "pbr": "ok"}, "267270": {"naver": true, "eps": "mismatch(4910 vs 9818.0)", "bps": "ok", "per": "mismatch(29.04 vs 14.52)", "pbr": "ok"}, "032640": {"naver": true, "eps": "ok", "bps": "ok", "per": "ok", "pbr": "ok"}, "078930": {"naver": true, "eps": "ok", "bps": "ok", "per": "ok", "pbr": "ok"}, "004170": {"naver": true, "eps": "ok", "bps": "ok", "per": "ok", "pbr": "ok"}, "009830": {"naver": true, "eps": "ok", "bps": "ok", "per": "ok_unverified", "pbr": "ok"}, "021240": {"naver": true, "eps": "ok", "bps": "ok", "per": "ok", "pbr": "ok"}, "241560": {"naver": true, "eps": "blank", "bps": "blank", "per": "blank", "pbr": "blank"}, "028300": {"naver": true, "eps": "ok", "bps": "ok", "per": "ok_unverified", "pbr": "ok"}, "000250": {"naver": true, "eps": "ok", "bps": "ok", "per": "ok", "pbr": "ok"}, "377300": {"naver": true, "eps": "ok", "bps": "ok", "per": "ok", "pbr": "ok"}, "403870": {"naver": true, "eps": "blank", "bps": "ok", "per": "blank", "pbr": "ok"}, "052690": {"naver": true, "eps": "ok", "bps": "ok", "per": "ok", "pbr": "ok"}, "036570": {"naver": true, "eps": "ok", "bps": "ok", "per": "ok", "pbr": "ok"}, "010060": {"naver": true, "eps": "ok", "bps": "ok", "per": "ok_unverified", "pbr": "ok"}, "023530": {"naver": true, "eps": "ok", "bps": "ok", "per": "ok", "pbr": "ok"}, "138930": {"naver": true, "eps": "ok", "bps": "ok", "per": "ok", "pbr": "ok"}, "066970": {"naver": true, "eps": "ok", "bps": "ok", "per": "ok_unverified", "pbr": "ok"}, "087010": {"naver": true, "eps": "blank", "bps": "ok", "per": "no_naver", "pbr": "ok"}, "271560": {"naver": true, "eps": "ok", "bps": "ok", "per": "ok", "pbr": "ok"}, "088980": {"naver": false, "eps": "no_naver", "bps": "no_naver", "per": "no_naver", "pbr": "no_naver"}, "128940": {"naver": true, "eps": "ok", "bps": "ok", "per": "ok", "pbr": "ok"}, "298380": {"naver": true, "eps": "blank", "bps": "ok", "per": "no_naver", "pbr": "ok"}, "440110": {"naver": true, "eps": "ok", "bps": "ok", "per": "ok_unverified", "pbr": "ok"}, "175330": {"naver": true, "eps": "ok", "bps": "ok", "per": "ok", "pbr": "ok"}, "319660": {"naver": true, "eps": "blank", "bps": "ok", "per": "blank", "pbr": "ok"}, "095340": {"naver": true, "eps": "ok", "bps": "ok", "per": "ok", "pbr": "ok"}, "222800": {"naver": true, "eps": "ok", "bps": "ok", "per": "ok_unverified", "pbr": "ok"}, "108490": {"naver": true, "eps": "ok", "bps": "ok", "per": "ok_unverified", "pbr": "ok"}, "336260": {"naver": true, "eps": "ok", "bps": "ok", "per": "ok_unverified", "pbr": "ok"}, "141080": {"naver": true, "eps": "blank", "bps": "ok", "per": "no_naver", "pbr": "ok"}, "178320": {"naver": true, "eps": "ok", "bps": "ok", "per": "ok_unverified", "pbr": "ok"}, "082740": {"naver": true, "eps": "blank", "bps": "ok", "per": "blank", "pbr": "ok"}, "084370": {"naver": true, "eps": "ok", "bps": "ok", "per": "ok", "pbr": "ok"}, "319400": {"naver": true, "eps": "ok", "bps": "ok", "per": "ok", "pbr": "ok"}, "002380": {"naver": true, "eps": "ok", "bps": "ok", "per": "ok", "pbr": "ok"}, "088350": {"naver": true, "eps": "ok", "bps": "ok", "per": "ok", "pbr": "ok"}, "022100": {"naver": true, "eps": "ok", "bps": "ok", "per": "ok", "pbr": "ok"}, "000500": {"naver": true, "eps": "ok", "bps": "ok", "per": "ok", "pbr": "ok"}, "214370": {"naver": true, "eps": "ok", "bps": "ok", "per": "ok", "pbr": "ok"}, "450080": {"naver": true, "eps": "blank", "bps": "ok", "per": "blank", "pbr": "ok"}, "103590": {"naver": true, "eps": "ok", "bps": "ok", "per": "ok", "pbr": "ok"}, "347850": {"naver": true, "eps": "ok", "bps": "ok", "per": "ok_unverified", "pbr": "ok"}, "310210": {"naver": true, "eps": "ok", "bps": "ok", "per": "ok_unverified", "pbr": "ok"}, "080220": {"naver": true, "eps": "ok", "bps": "ok", "per": "ok", "pbr": "ok"}, "095610": {"naver": true, "eps": "ok", "bps": "ok", "per": "ok", "pbr": "ok"}, "012510": {"naver": true, "eps": "ok", "bps": "ok", "per": "ok", "pbr": "ok"}, "251270": {"naver": true, "eps": "ok", "bps": "ok", "per": "ok", "pbr": "ok"}, "357780": {"naver": true, "eps": "ok", "bps": "ok", "per": "ok", "pbr": "ok"}, "131970": {"naver": true, "eps": "blank", "bps": "ok", "per": "blank", "pbr": "ok"}, "012750": {"naver": true, "eps": "ok", "bps": "ok", "per": "ok", "pbr": "ok"}, "035250": {"naver": true, "eps": "ok", "bps": "ok", "per": "ok", "pbr": "ok"}, "036460": {"naver": true, "eps": "ok", "bps": "ok", "per": "ok", "pbr": "ok"}, "043260": {"naver": true, "eps": "blank", "bps": "ok", "per": "blank", "pbr": "ok"}, "383220": {"naver": true, "eps": "ok", "bps": "ok", "per": "ok", "pbr": "ok"}, "031980": {"naver": true, "eps": "blank", "bps": "ok", "per": "blank", "pbr": "ok"}, "064760": {"naver": true, "eps": "blank", "bps": "ok", "per": "blank", "pbr": "ok"}, "031210": {"naver": true, "eps": "ok", "bps": "ok", "per": "ok", "pbr": "ok"}, "007810": {"naver": true, "eps": "ok", "bps": "ok", "per": "ok", "pbr": "ok"}, "014680": {"naver": true, "eps": "ok", "bps": "ok", "per": "ok", "pbr": "ok"}, "005850": {"naver": true, "eps": "ok", "bps": "ok", "per": "ok", "pbr": "ok"}, "017800": {"naver": true, "eps": "ok", "bps": "ok", "per": "ok", "pbr": "ok"}, "302440": {"naver": true, "eps": "ok", "bps": "ok", "per": "ok_unverified", "pbr": "ok"}, "204320": {"naver": true, "eps": "ok", "bps": "ok", "per": "ok", "pbr": "ok"}, "004800": {"naver": true, "eps": "ok", "bps": "ok", "per": "ok", "pbr": "ok"}, "032820": {"naver": true, "eps": "ok", "bps": "ok", "per": "ok", "pbr": "ok"}, "145020": {"naver": true, "eps": "ok", "bps": "ok", "per": "ok", "pbr": "ok"}, "005290": {"naver": true, "eps": "ok", "bps": "ok", "per": "ok", "pbr": "ok"}, "214450": {"naver": true, "eps": "ok", "bps": "ok", "per": "ok", "pbr": "ok"}, "131290": {"naver": true, "eps": "ok", "bps": "ok", "per": "ok", "pbr": "ok"}, "020150": {"naver": true, "eps": "ok", "bps": "ok", "per": "ok_unverified", "pbr": "ok"}, "051600": {"naver": true, "eps": "ok", "bps": "ok", "per": "ok", "pbr": "ok"}, "214150": {"naver": true, "eps": "ok", "bps": "ok", "per": "ok", "pbr": "ok"}, "139130": {"naver": true, "eps": "ok", "bps": "ok", "per": "ok", "pbr": "ok"}, "028670": {"naver": true, "eps": "blank", "bps": "ok", "per": "blank", "pbr": "ok"}, "009420": {"naver": true, "eps": "ok", "bps": "ok", "per": "ok_unverified", "pbr": "ok"}, "098460": {"naver": true, "eps": "ok", "bps": "ok", "per": "ok", "pbr": "ok"}, "279570": {"naver": true, "eps": "blank", "bps": "ok", "per": "blank", "pbr": "ok"}, "263750": {"naver": true, "eps": "ok", "bps": "ok", "per": "ok", "pbr": "ok"}, "001740": {"naver": true, "eps": "ok", "bps": "ok", "per": "ok", "pbr": "ok"}, "000240": {"naver": true, "eps": "ok", "bps": "ok", "per": "ok", "pbr": "ok"}, "237690": {"naver": true, "eps": "ok", "bps": "ok", "per": "ok", "pbr": "ok"}, "026960": {"naver": true, "eps": "ok", "bps": "ok", "per": "ok", "pbr": "ok"}, "457190": {"naver": true, "eps": "blank", "bps": "ok", "per": "no_naver", "pbr": "ok"}, "083650": {"naver": true, "eps": "ok", "bps": "ok", "per": "ok", "pbr": "ok"}, "139480": {"naver": true, "eps": "ok", "bps": "ok", "per": "ok", "pbr": "ok"}, "009970": {"naver": true, "eps": "ok", "bps": "ok", "per": "ok", "pbr": "ok"}, "483650": {"naver": true, "eps": "ok", "bps": "ok", "per": "ok", "pbr": "ok"}, "089970": {"naver": true, "eps": "blank", "bps": "ok", "per": "blank", "pbr": "ok"}, "003690": {"naver": true, "eps": "blank", "bps": "ok", "per": "blank", "pbr": "ok"}, "030530": {"naver": true, "eps": "ok", "bps": "ok", "per": "ok", "pbr": "ok"}, "140860": {"naver": true, "eps": "ok", "bps": "ok", "per": "ok", "pbr": "ok"}, "007340": {"naver": true, "eps": "ok", "bps": "ok", "per": "ok", "pbr": "ok"}, "439260": {"naver": true, "eps": "blank", "bps": "ok", "per": "blank", "pbr": "ok"}, "030000": {"naver": true, "eps": "ok", "bps": "ok", "per": "ok", "pbr": "ok"}, "226950": {"naver": true, "eps": "ok", "bps": "ok", "per": "ok_unverified", "pbr": "ok"}, "004370": {"naver": true, "eps": "ok", "bps": "ok", "per": "ok", "pbr": "ok"}, "257720": {"naver": true, "eps": "ok", "bps": "ok", "per": "ok", "pbr": "ok"}, "071970": {"naver": true, "eps": "ok", "bps": "ok", "per": "ok", "pbr": "ok"}, "282330": {"naver": true, "eps": "ok", "bps": "ok", "per": "ok", "pbr": "ok"}, "120110": {"naver": true, "eps": "ok", "bps": "ok", "per": "ok", "pbr": "ok"}, "008770": {"naver": true, "eps": "ok", "bps": "ok", "per": "ok_unverified", "pbr": "ok"}, "005440": {"naver": true, "eps": "ok", "bps": "ok", "per": "ok", "pbr": "ok"}, "082920": {"naver": true, "eps": "blank", "bps": "ok", "per": "blank", "pbr": "ok"}, "058610": {"naver": true, "eps": "ok", "bps": "ok", "per": "ok", "pbr": "ok"}, "011210": {"naver": true, "eps": "ok", "bps": "ok", "per": "ok", "pbr": "ok"}, "103140": {"naver": true, "eps": "ok", "bps": "ok", "per": "ok", "pbr": "ok"}, "007390": {"naver": true, "eps": "ok", "bps": "ok", "per": "ok_unverified", "pbr": "ok"}, "100790": {"naver": true, "eps": "blank", "bps": "ok", "per": "blank", "pbr": "ok"}, "008930": {"naver": true, "eps": "ok", "bps": "ok", "per": "ok", "pbr": "ok"}, "018670": {"naver": true, "eps": "ok", "bps": "ok", "per": "ok", "pbr": "ok"}, "007070": {"naver": true, "eps": "ok", "bps": "ok", "per": "ok", "pbr": "ok"}, "218410": {"naver": true, "eps": "ok", "bps": "ok", "per": "ok", "pbr": "ok"}, "161890": {"naver": true, "eps": "ok", "bps": "ok", "per": "ok", "pbr": "ok"}, "035900": {"naver": true, "eps": "ok", "bps": "ok", "per": "ok", "pbr": "ok"}, "140410": {"naver": true, "eps": "blank", "bps": "ok", "per": "no_naver", "pbr": "ok"}, "097230": {"naver": true, "eps": "ok", "bps": "ok", "per": "ok", "pbr": "ok"}, "041510": {"naver": true, "eps": "ok", "bps": "ok", "per": "ok", "pbr": "ok"}, "192820": {"naver": true, "eps": "ok", "bps": "ok", "per": "ok", "pbr": "ok"}, "068760": {"naver": true, "eps": "blank", "bps": "ok", "per": "blank", "pbr": "ok"}, "347700": {"naver": true, "eps": "blank", "bps": "ok", "per": "blank", "pbr": "ok"}, "229640": {"naver": true, "eps": "ok", "bps": "ok", "per": "ok", "pbr": "ok"}, "462870": {"naver": true, "eps": "blank", "bps": "ok", "per": "blank", "pbr": "ok"}, "420770": {"naver": true, "eps": "blank", "bps": "ok", "per": "blank", "pbr": "ok"}, "0009K0": {"naver": true, "eps": "blank", "bps": "blank", "per": "blank", "pbr": "blank"}, "112610": {"naver": true, "eps": "ok", "bps": "ok", "per": "ok_unverified", "pbr": "ok"}, "281820": {"naver": true, "eps": "blank", "bps": "ok", "per": "blank", "pbr": "ok"}, "001430": {"naver": true, "eps": "ok", "bps": "ok", "per": "ok", "pbr": "ok"}, "023590": {"naver": true, "eps": "ok", "bps": "ok", "per": "ok", "pbr": "ok"}, "322000": {"naver": true, "eps": "blank", "bps": "ok", "per": "blank", "pbr": "ok"}, "017960": {"naver": true, "eps": "ok", "bps": "ok", "per": "ok", "pbr": "ok"}, "323280": {"naver": true, "eps": "blank", "bps": "ok", "per": "no_naver", "pbr": "ok"}, "001800": {"naver": true, "eps": "ok", "bps": "ok", "per": "ok", "pbr": "ok"}, "060370": {"naver": true, "eps": "blank", "bps": "ok", "per": "blank", "pbr": "ok"}, "001120": {"naver": true, "eps": "ok", "bps": "ok", "per": "ok", "pbr": "ok"}, "361610": {"naver": true, "eps": "ok", "bps": "ok", "per": "ok_unverified", "pbr": "ok"}, "192080": {"naver": true, "eps": "ok", "bps": "ok", "per": "ok", "pbr": "ok"}, "005070": {"naver": true, "eps": "blank", "bps": "ok", "per": "no_naver", "pbr": "ok"}, "031330": {"naver": true, "eps": "blank", "bps": "ok", "per": "blank", "pbr": "ok"}, "006040": {"naver": true, "eps": "ok", "bps": "ok", "per": "ok", "pbr": "ok"}, "006280": {"naver": true, "eps": "mismatch(-554 vs -1189.0)", "bps": "ok", "per": "ok_unverified", "pbr": "ok"}, "475150": {"naver": true, "eps": "ok", "bps": "ok", "per": "ok", "pbr": "ok"}, "475830": {"naver": true, "eps": "blank", "bps": "ok", "per": "no_naver", "pbr": "ok"}, "003540": {"naver": true, "eps": "ok", "bps": "ok", "per": "ok", "pbr": "ok"}, "020560": {"naver": true, "eps": "ok", "bps": "ok", "per": "ok_unverified", "pbr": "ok"}, "298020": {"naver": true, "eps": "ok", "bps": "ok", "per": "ok", "pbr": "ok"}, "166090": {"naver": true, "eps": "ok", "bps": "ok", "per": "ok", "pbr": "ok"}, "032350": {"naver": true, "eps": "ok", "bps": "ok", "per": "ok", "pbr": "ok"}, "069620": {"naver": true, "eps": "ok", "bps": "ok", "per": "ok", "pbr": "ok"}, "034230": {"naver": true, "eps": "ok", "bps": "ok", "per": "ok", "pbr": "ok"}, "073240": {"naver": true, "eps": "ok", "bps": "ok", "per": "ok", "pbr": "ok"}, "101490": {"naver": true, "eps": "ok", "bps": "ok", "per": "ok", "pbr": "ok"}, "003570": {"naver": true, "eps": "ok", "bps": "ok", "per": "ok", "pbr": "ok"}, "195870": {"naver": true, "eps": "ok", "bps": "ok", "per": "ok", "pbr": "ok"}, "001820": {"naver": true, "eps": "ok", "bps": "ok", "per": "ok", "pbr": "ok"}, "007310": {"naver": true, "eps": "ok", "bps": "ok", "per": "ok", "pbr": "ok"}, "294870": {"naver": true, "eps": "ok", "bps": "ok", "per": "ok", "pbr": "ok"}, "232140": {"naver": true, "eps": "ok", "bps": "ok", "per": "ok", "pbr": "ok"}, "181710": {"naver": true, "eps": "ok", "bps": "ok", "per": "ok", "pbr": "ok"}, "077970": {"naver": true, "eps": "ok", "bps": "ok", "per": "ok", "pbr": "ok"}, "099320": {"naver": true, "eps": "ok", "bps": "ok", "per": "ok", "pbr": "ok"}, "476830": {"naver": true, "eps": "blank", "bps": "ok", "per": "no_naver", "pbr": "ok"}, "012630": {"naver": true, "eps": "ok", "bps": "ok", "per": "ok", "pbr": "ok"}, "003530": {"naver": true, "eps": "blank", "bps": "ok", "per": "blank", "pbr": "ok"}, "030610": {"naver": true, "eps": "ok", "bps": "ok", "per": "ok", "pbr": "ok"}, "038500": {"naver": true, "eps": "ok", "bps": "ok", "per": "ok", "pbr": "ok"}, "295310": {"naver": true, "eps": "blank", "bps": "ok", "per": "blank", "pbr": "ok"}, "004000": {"naver": true, "eps": "ok", "bps": "ok", "per": "ok", "pbr": "ok"}, "082640": {"naver": true, "eps": "blank", "bps": "mismatch(11429 vs 9925.0)", "per": "blank", "pbr": "mismatch(0.68 vs 0.78)"}, "415640": {"naver": false, "eps": "no_naver", "bps": "no_naver", "per": "no_naver", "pbr": "no_naver"}, "083450": {"naver": true, "eps": "ok", "bps": "ok", "per": "ok", "pbr": "ok"}, "036540": {"naver": true, "eps": "blank", "bps": "ok", "per": "no_naver", "pbr": "ok"}, "445680": {"naver": true, "eps": "ok", "bps": "ok", "per": "ok_unverified", "pbr": "ok"}, "195940": {"naver": true, "eps": "blank", "bps": "ok", "per": "blank", "pbr": "ok"}, "032500": {"naver": true, "eps": "ok", "bps": "ok", "per": "ok_unverified", "pbr": "ok"}, "003380": {"naver": true, "eps": "ok", "bps": "ok", "per": "ok", "pbr": "ok"}, "000080": {"naver": true, "eps": "ok", "bps": "ok", "per": "ok", "pbr": "ok"}, "388210": {"naver": true, "eps": "blank", "bps": "ok", "per": "no_naver", "pbr": "ok"}, "127120": {"naver": true, "eps": "mismatch(-456 vs -525.0)", "bps": "ok", "per": "ok_unverified", "pbr": "ok"}, "000210": {"naver": true, "eps": "ok", "bps": "ok", "per": "ok_unverified", "pbr": "ok"}, "065350": {"naver": true, "eps": "ok", "bps": "ok", "per": "ok", "pbr": "ok"}, "189300": {"naver": true, "eps": "ok", "bps": "ok", "per": "ok", "pbr": "ok"}, "417200": {"naver": true, "eps": "ok", "bps": "ok", "per": "ok", "pbr": "ok"}, "458870": {"naver": true, "eps": "blank", "bps": "ok", "per": "blank", "pbr": "ok"}, "089860": {"naver": true, "eps": "ok", "bps": "ok", "per": "ok", "pbr": "ok"}, "074600": {"naver": true, "eps": "blank", "bps": "mismatch(22085 vs 19354.0)", "per": "blank", "pbr": "mismatch(1.91 vs 2.18)"}, "085660": {"naver": true, "eps": "ok", "bps": "mismatch(7670 vs 5534.0)", "per": "ok_unverified", "pbr": "mismatch(1.55 vs 2.15)"}, "090360": {"naver": true, "eps": "blank", "bps": "ok", "per": "no_naver", "pbr": "ok"}, "328130": {"naver": true, "eps": "mismatch(-2297 vs -1074.0)", "bps": "mismatch(4258 vs 1992.0)", "per": "ok_unverified", "pbr": "mismatch(3.47 vs 7.41)"}, "330590": {"naver": true, "eps": "blank", "bps": "mismatch(1971 vs 3857.0)", "per": "blank", "pbr": "mismatch(1.92 vs 0.98)"}, "281740": {"naver": true, "eps": "ok", "bps": "ok", "per": "ok", "pbr": "ok"}, "300720": {"naver": true, "eps": "ok", "bps": "ok", "per": "ok", "pbr": "ok"}, "003240": {"naver": true, "eps": "ok", "bps": "mismatch(3595707 vs 4756789.0)", "per": "ok", "pbr": "mismatch(0.26 vs 0.2)"}, "003090": {"naver": true, "eps": "ok", "bps": "ok", "per": "ok", "pbr": "ok"}, "496320": {"naver": false, "eps": "no_naver", "bps": "no_naver", "per": "no_naver", "pbr": "no_naver"}, "491000": {"naver": true, "eps": "blank", "bps": "ok", "per": "no_naver", "pbr": "ok"}, "124500": {"naver": true, "eps": "ok", "bps": "ok", "per": "ok", "pbr": "ok"}, "280360": {"naver": true, "eps": "ok", "bps": "ok", "per": "ok", "pbr": "ok"}, "027360": {"naver": true, "eps": "ok", "bps": "ok", "per": "ok", "pbr": "ok"}, "036830": {"naver": true, "eps": "blank", "bps": "ok", "per": "blank", "pbr": "ok"}, "009450": {"naver": true, "eps": "blank", "bps": "ok", "per": "blank", "pbr": "ok"}, "161580": {"naver": true, "eps": "ok", "bps": "ok", "per": "ok_unverified", "pbr": "ok"}, "137400": {"naver": true, "eps": "ok", "bps": "ok", "per": "ok", "pbr": "ok"}, "356860": {"naver": true, "eps": "ok", "bps": "ok", "per": "ok", "pbr": "ok"}, "388720": {"naver": true, "eps": "blank", "bps": "ok", "per": "no_naver", "pbr": "ok"}, "252990": {"naver": true, "eps": "blank", "bps": "ok", "per": "blank", "pbr": "ok"}, "490470": {"naver": true, "eps": "blank", "bps": "mismatch(8067 vs 6769.0)", "per": "no_naver", "pbr": "mismatch(3.58 vs 4.26)"}, "005300": {"naver": true, "eps": "mismatch(7130 vs 6423.0)", "bps": "mismatch(164764 vs 152059.0)", "per": "mismatch(14.81 vs 16.44)", "pbr": "ok"}, "100090": {"naver": true, "eps": "ok", "bps": "ok", "per": "ok", "pbr": "ok"}, "185750": {"naver": true, "eps": "ok", "bps": "ok", "per": "ok", "pbr": "ok"}, "057050": {"naver": true, "eps": "ok", "bps": "ok", "per": "ok", "pbr": "ok"}, "397030": {"naver": true, "eps": "blank", "bps": "ok", "per": "no_naver", "pbr": "ok"}, "003470": {"naver": true, "eps": "ok", "bps": "ok", "per": "ok", "pbr": "ok"}, "056190": {"naver": true, "eps": "ok", "bps": "ok", "per": "ok", "pbr": "ok"}, "499790": {"naver": true, "eps": "ok", "bps": "ok", "per": "ok", "pbr": "ok"}, "115180": {"naver": true, "eps": "ok", "bps": "ok", "per": "ok_unverified", "pbr": "ok"}, "204270": {"naver": true, "eps": "ok", "bps": "ok", "per": "ok_unverified", "pbr": "ok"}, "456040": {"naver": true, "eps": "ok", "bps": "ok", "per": "ok_unverified", "pbr": "ok"}, "466100": {"naver": true, "eps": "blank", "bps": "ok", "per": "no_naver", "pbr": "ok"}, "192400": {"naver": true, "eps": "ok", "bps": "ok", "per": "ok", "pbr": "ok"}, "213420": {"naver": true, "eps": "ok", "bps": "ok", "per": "ok", "pbr": "ok"}, "248070": {"naver": true, "eps": "mismatch(304 vs 263.0)", "bps": "mismatch(11619 vs 10141.0)", "per": "mismatch(62.5 vs 72.24)", "pbr": "mismatch(1.64 vs 1.87)"}, "090460": {"naver": true, "eps": "ok", "bps": "mismatch(27986 vs 23988.0)", "per": "ok", "pbr": "mismatch(0.96 vs 1.12)"}, "006110": {"naver": true, "eps": "ok", "bps": "ok", "per": "ok_unverified", "pbr": "ok"}, "365550": {"naver": true, "eps": "blank", "bps": "ok", "per": "blank", "pbr": "ok"}, "298050": {"naver": true, "eps": "mismatch(4458 vs -3834.0)", "bps": "ok", "per": "ok_unverified", "pbr": "ok"}, "005690": {"naver": true, "eps": "blank", "bps": "ok", "per": "blank", "pbr": "ok"}, "000670": {"naver": true, "eps": "ok", "bps": "ok", "per": "ok_unverified", "pbr": "ok"}, "086450": {"naver": true, "eps": "ok", "bps": "ok", "per": "ok", "pbr": "ok"}, "137310": {"naver": true, "eps": "ok", "bps": "ok", "per": "ok_unverified", "pbr": "ok"}, "030190": {"naver": true, "eps": "ok", "bps": "ok", "per": "ok", "pbr": "ok"}, "048410": {"naver": true, "eps": "ok", "bps": "ok", "per": "ok_unverified", "pbr": "ok"}, "122870": {"naver": true, "eps": "ok", "bps": "ok", "per": "ok", "pbr": "ok"}, "336370": {"naver": true, "eps": "mismatch(-769 vs -475.0)", "bps": "mismatch(10103 vs 7805.0)", "per": "ok_unverified", "pbr": "mismatch(1.21 vs 1.56)"}, "160190": {"naver": true, "eps": "ok", "bps": "ok", "per": "ok_unverified", "pbr": "ok"}, "214320": {"naver": true, "eps": "ok", "bps": "ok", "per": "ok", "pbr": "ok"}, "005090": {"naver": true, "eps": "ok", "bps": "ok", "per": "ok_unverified", "pbr": "ok"}, "035760": {"naver": true, "eps": "mismatch(3885 vs 4455.0)", "bps": "ok", "per": "mismatch(9.81 vs 8.55)", "pbr": "ok"}, "075580": {"naver": true, "eps": "ok", "bps": "ok", "per": "ok", "pbr": "ok"}, "376900": {"naver": true, "eps": "mismatch(-259 vs -282.0)", "bps": "ok", "per": "ok_unverified", "pbr": "ok"}, "079900": {"naver": true, "eps": "mismatch(1920 vs 2134.0)", "bps": "mismatch(11839 vs 10516.0)", "per": "mismatch(29.79 vs 26.8)", "pbr": "mismatch(4.83 vs 5.44)"}, "222080": {"naver": true, "eps": "ok", "bps": "ok", "per": "ok", "pbr": "ok"}, "033100": {"naver": true, "eps": "blank", "bps": "ok", "per": "blank", "pbr": "ok"}, "036530": {"naver": true, "eps": "ok", "bps": "ok", "per": "ok", "pbr": "ok"}, "071320": {"naver": true, "eps": "ok", "bps": "ok", "per": "ok", "pbr": "ok"}, "006340": {"naver": true, "eps": "ok", "bps": "ok", "per": "ok", "pbr": "ok"}, "484870": {"naver": true, "eps": "blank", "bps": "ok", "per": "blank", "pbr": "ok"}, "108320": {"naver": true, "eps": "ok", "bps": "ok", "per": "ok", "pbr": "ok"}, "006650": {"naver": true, "eps": "ok", "bps": "ok", "per": "ok", "pbr": "ok"}, "451800": {"naver": true, "eps": "blank", "bps": "mismatch(1938 vs 3793.0)", "per": "blank", "pbr": "mismatch(2.32 vs 1.19)"}, "006120": {"naver": true, "eps": "mismatch(14436 vs 12649.0)", "bps": "ok", "per": "mismatch(3.21 vs 3.67)", "pbr": "ok"}, "003160": {"naver": true, "eps": "ok", "bps": "ok", "per": "ok", "pbr": "ok"}, "053610": {"naver": true, "eps": "mismatch(4650 vs 5553.0)", "bps": "ok", "per": "mismatch(19.2 vs 16.08)", "pbr": "ok"}, "293490": {"naver": true, "eps": "ok", "bps": "ok", "per": "ok_unverified", "pbr": "ok"}, "014620": {"naver": true, "eps": "ok", "bps": "ok", "per": "ok", "pbr": "ok"}, "171090": {"naver": true, "eps": "blank", "bps": "ok", "per": "blank", "pbr": "ok"}, "064960": {"naver": true, "eps": "ok", "bps": "ok", "per": "ok", "pbr": "ok"}, "009240": {"naver": true, "eps": "ok", "bps": "ok", "per": "ok", "pbr": "ok"}, "050890": {"naver": true, "eps": "ok", "bps": "ok", "per": "ok", "pbr": "ok"}, "094170": {"naver": true, "eps": "blank", "bps": "ok", "per": "blank", "pbr": "ok"}, "010780": {"naver": true, "eps": "ok", "bps": "ok", "per": "ok", "pbr": "ok"}, "001510": {"naver": true, "eps": "mismatch(103 vs 207.0)", "bps": "mismatch(1313 vs 2884.0)", "per": "mismatch(32.48 vs 16.16)", "pbr": "mismatch(2.55 vs 1.16)"}, "046890": {"naver": true, "eps": "ok", "bps": "ok", "per": "ok_unverified", "pbr": "ok"}, "348370": {"naver": true, "eps": "ok", "bps": "ok", "per": "ok_unverified", "pbr": "ok"}, "023160": {"naver": true, "eps": "ok", "bps": "ok", "per": "ok", "pbr": "ok"}, "358570": {"naver": true, "eps": "blank", "bps": "ok", "per": "no_naver", "pbr": "ok"}, "285130": {"naver": true, "eps": "mismatch(-248 vs 646.0)", "bps": "ok", "per": "mismatch(-177.62 vs 68.19)", "pbr": "ok"}, "000370": {"naver": true, "eps": "mismatch(2308 vs 1747.0)", "bps": "mismatch(24501 vs 17378.0)", "per": "mismatch(2.82 vs 3.72)", "pbr": "mismatch(0.27 vs 0.37)"}, "033790": {"naver": true, "eps": "blank", "bps": "ok", "per": "blank", "pbr": "ok"}, "126340": {"naver": true, "eps": "ok", "bps": "ok", "per": "ok_unverified", "pbr": "ok"}, "253450": {"naver": true, "eps": "ok", "bps": "ok", "per": "ok", "pbr": "ok"}, "033240": {"naver": true, "eps": "ok", "bps": "ok", "per": "ok", "pbr": "ok"}, "456160": {"naver": true, "eps": "blank", "bps": "ok", "per": "no_naver", "pbr": "ok"}, "033640": {"naver": true, "eps": "ok", "bps": "ok", "per": "ok", "pbr": "ok"}, "032190": {"naver": true, "eps": "ok", "bps": "ok", "per": "ok", "pbr": "ok"}, "052020": {"naver": true, "eps": "ok", "bps": "ok", "per": "ok_unverified", "pbr": "ok"}, "114090": {"naver": true, "eps": "ok", "bps": "ok", "per": "ok", "pbr": "ok"}, "003850": {"naver": true, "eps": "ok", "bps": "ok", "per": "ok", "pbr": "ok"}, "079160": {"naver": true, "eps": "mismatch(-793 vs -883.0)", "bps": "ok", "per": "ok_unverified", "pbr": "ok"}, "102710": {"naver": true, "eps": "ok", "bps": "ok", "per": "ok", "pbr": "ok"}, "004490": {"naver": true, "eps": "ok", "bps": "ok", "per": "ok", "pbr": "ok"}, "025540": {"naver": true, "eps": "ok", "bps": "ok", "per": "ok", "pbr": "ok"}, "241710": {"naver": true, "eps": "ok", "bps": "ok", "per": "ok", "pbr": "ok"}, "056080": {"naver": true, "eps": "blank", "bps": "ok", "per": "no_naver", "pbr": "ok"}, "052400": {"naver": true, "eps": "ok", "bps": "ok", "per": "ok", "pbr": "ok"}, "002350": {"naver": true, "eps": "ok", "bps": "ok", "per": "ok", "pbr": "ok"}, "006730": {"naver": true, "eps": "ok", "bps": "ok", "per": "ok", "pbr": "ok"}, "036810": {"naver": true, "eps": "ok", "bps": "ok", "per": "ok_unverified", "pbr": "ok"}, "476060": {"naver": true, "eps": "blank", "bps": "ok", "per": "blank", "pbr": "ok"}, "121600": {"naver": true, "eps": "ok", "bps": "ok", "per": "ok", "pbr": "ok"}, "425420": {"naver": true, "eps": "blank", "bps": "ok", "per": "blank", "pbr": "ok"}, "059090": {"naver": true, "eps": "mismatch(502 vs 199.0)", "bps": "ok", "per": "mismatch(41.83 vs 105.53)", "pbr": "ok"}, "178920": {"naver": true, "eps": "blank", "bps": "ok", "per": "blank", "pbr": "ok"}, "100840": {"naver": true, "eps": "ok", "bps": "ok", "per": "ok", "pbr": "ok"}, "093050": {"naver": true, "eps": "ok", "bps": "ok", "per": "ok", "pbr": "ok"}, "399720": {"naver": true, "eps": "ok", "bps": "ok", "per": "ok_unverified", "pbr": "ok"}, "037460": {"naver": true, "eps": "ok", "bps": "ok", "per": "ok", "pbr": "ok"}, "365340": {"naver": true, "eps": "ok", "bps": "ok", "per": "ok_unverified", "pbr": "ok"}, "002960": {"naver": true, "eps": "blank", "bps": "ok", "per": "blank", "pbr": "ok"}, "293940": {"naver": true, "eps": "blank", "bps": "mismatch(2626 vs 4993.0)", "per": "blank", "pbr": "mismatch(2.1 vs 1.1)"}, "002020": {"naver": true, "eps": "ok", "bps": "ok", "per": "ok_unverified", "pbr": "ok"}, "033160": {"naver": true, "eps": "ok", "bps": "ok", "per": "ok", "pbr": "ok"}, "077360": {"naver": true, "eps": "blank", "bps": "ok", "per": "no_naver", "pbr": "ok"}, "005880": {"naver": true, "eps": "ok", "bps": "ok", "per": "ok", "pbr": "ok"}, "102940": {"naver": true, "eps": "ok", "bps": "ok", "per": "ok", "pbr": "ok"}, "044490": {"naver": true, "eps": "blank", "bps": "ok", "per": "blank", "pbr": "ok"}, "007700": {"naver": true, "eps": "ok", "bps": "ok", "per": "ok", "pbr": "ok"}, "003620": {"naver": true, "eps": "ok", "bps": "ok", "per": "ok", "pbr": "ok"}, "348210": {"naver": true, "eps": "ok", "bps": "mismatch(16688 vs 14178.0)", "per": "ok_unverified", "pbr": "mismatch(3.68 vs 4.33)"}, "001680": {"naver": true, "eps": "ok", "bps": "ok", "per": "ok_unverified", "pbr": "ok"}, "001270": {"naver": true, "eps": "blank", "bps": "mismatch(61268 vs 93587.0)", "per": "blank", "pbr": "mismatch(1.01 vs 0.66)"}, "008060": {"naver": true, "eps": "ok", "bps": "mismatch(15938 vs 18715.0)", "per": "ok", "pbr": "mismatch(1.29 vs 1.1)"}, "069260": {"naver": true, "eps": "ok", "bps": "ok", "per": "ok", "pbr": "ok"}, "122640": {"naver": true, "eps": "ok", "bps": "ok", "per": "ok", "pbr": "ok"}, "225570": {"naver": true, "eps": "blank", "bps": "ok", "per": "no_naver", "pbr": "ok"}, "053800": {"naver": true, "eps": "ok", "bps": "mismatch(52567 vs 40749.0)", "per": "ok", "pbr": "mismatch(1.09 vs 1.41)"}, "014820": {"naver": true, "eps": "ok", "bps": "ok", "per": "ok", "pbr": "ok"}, "005180": {"naver": true, "eps": "ok", "bps": "ok", "per": "ok", "pbr": "ok"}, "001570": {"naver": true, "eps": "ok", "bps": "ok", "per": "ok_unverified", "pbr": "ok"}, "317450": {"naver": true, "eps": "blank", "bps": "ok", "per": "blank", "pbr": "ok"}, "041960": {"naver": true, "eps": "ok", "bps": "mismatch(1233 vs 985.0)", "per": "ok_unverified", "pbr": "mismatch(6.94 vs 8.69)"}, "336570": {"naver": true, "eps": "ok", "bps": "ok", "per": "ok", "pbr": "ok"}, "001060": {"naver": true, "eps": "ok", "bps": "ok", "per": "ok", "pbr": "ok"}, "089890": {"naver": true, "eps": "ok", "bps": "ok", "per": "ok", "pbr": "ok"}, "439960": {"naver": true, "eps": "blank", "bps": "ok", "per": "no_naver", "pbr": "ok"}, "009520": {"naver": true, "eps": "blank", "bps": "ok", "per": "blank", "pbr": "ok"}, "383800": {"naver": true, "eps": "ok", "bps": "ok", "per": "ok", "pbr": "ok"}, "086900": {"naver": true, "eps": "ok", "bps": "ok", "per": "ok", "pbr": "ok"}, "006380": {"naver": true, "eps": "blank", "bps": "ok", "per": "no_naver", "pbr": "ok"}, "330860": {"naver": true, "eps": "blank", "bps": "ok", "per": "blank", "pbr": "ok"}, "348340": {"naver": true, "eps": "ok", "bps": "ok", "per": "ok_unverified", "pbr": "ok"}, "253590": {"naver": true, "eps": "blank", "bps": "ok", "per": "blank", "pbr": "ok"}, "016380": {"naver": true, "eps": "ok", "bps": "ok", "per": "ok", "pbr": "ok"}, "093320": {"naver": true, "eps": "ok", "bps": "ok", "per": "ok", "pbr": "ok"}, "249420": {"naver": true, "eps": "mismatch(966 vs 1143.0)", "bps": "mismatch(8800 vs 7863.0)", "per": "mismatch(19.95 vs 16.86)", "pbr": "mismatch(2.19 vs 2.45)"}, "112040": {"naver": true, "eps": "mismatch(645 vs 758.0)", "bps": "mismatch(12569 vs 11472.0)", "per": "mismatch(27.81 vs 23.67)", "pbr": "mismatch(1.43 vs 1.56)"}, "060250": {"naver": true, "eps": "ok", "bps": "ok", "per": "ok", "pbr": "ok"}, "017940": {"naver": true, "eps": "ok", "bps": "ok", "per": "ok", "pbr": "ok"}, "104830": {"naver": true, "eps": "ok", "bps": "ok", "per": "ok", "pbr": "ok"}, "170920": {"naver": true, "eps": "ok", "bps": "ok", "per": "ok", "pbr": "ok"}, "041830": {"naver": true, "eps": "ok", "bps": "ok", "per": "ok", "pbr": "ok"}, "389470": {"naver": true, "eps": "mismatch(45 vs 225.0)", "bps": "mismatch(8191 vs 6527.0)", "per": "mismatch(996.67 vs 199.33)", "pbr": "mismatch(5.48 vs 6.87)"}, "174900": {"naver": true, "eps": "blank", "bps": "ok", "per": "no_naver", "pbr": "ok"}, "019210": {"naver": true, "eps": "ok", "bps": "ok", "per": "ok", "pbr": "ok"}, "383310": {"naver": true, "eps": "blank", "bps": "ok", "per": "blank", "pbr": "ok"}, "000400": {"naver": true, "eps": "blank", "bps": "ok", "per": "blank", "pbr": "ok"}, "082270": {"naver": true, "eps": "blank", "bps": "ok", "per": "no_naver", "pbr": "ok"}, "045100": {"naver": true, "eps": "ok", "bps": "ok", "per": "ok", "pbr": "ok"}, "486990": {"naver": true, "eps": "blank", "bps": "mismatch(0 vs 1118.0)", "per": "no_naver", "pbr": "blank"}, "453340": {"naver": true, "eps": "ok", "bps": "ok", "per": "ok", "pbr": "ok"}, "272290": {"naver": true, "eps": "ok", "bps": "ok", "per": "ok", "pbr": "ok"}, "001500": {"naver": true, "eps": "ok", "bps": "mismatch(23255 vs 26343.0)", "per": "ok", "pbr": "mismatch(0.4 vs 0.35)"}, "002840": {"naver": true, "eps": "ok", "bps": "ok", "per": "ok", "pbr": "ok"}, "003030": {"naver": true, "eps": "ok", "bps": "ok", "per": "ok", "pbr": "ok"}, "327260": {"naver": true, "eps": "ok", "bps": "ok", "per": "ok", "pbr": "ok"}, "376300": {"naver": true, "eps": "ok", "bps": "ok", "per": "ok", "pbr": "ok"}, "168360": {"naver": true, "eps": "ok", "bps": "ok", "per": "ok_unverified", "pbr": "ok"}, "033500": {"naver": true, "eps": "ok", "bps": "ok", "per": "ok", "pbr": "ok"}, "058650": {"naver": true, "eps": "ok", "bps": "ok", "per": "ok", "pbr": "ok"}, "039130": {"naver": true, "eps": "ok", "bps": "ok", "per": "ok", "pbr": "ok"}, "015750": {"naver": true, "eps": "blank", "bps": "ok", "per": "blank", "pbr": "ok"}, "000640": {"naver": true, "eps": "ok", "bps": "ok", "per": "ok", "pbr": "ok"}, "031430": {"naver": true, "eps": "blank", "bps": "ok", "per": "blank", "pbr": "ok"}, "067160": {"naver": true, "eps": "ok", "bps": "ok", "per": "ok", "pbr": "ok"}, "064290": {"naver": true, "eps": "ok", "bps": "ok", "per": "ok", "pbr": "ok"}, "200710": {"naver": true, "eps": "ok", "bps": "mismatch(18382 vs 10551.0)", "per": "ok", "pbr": "mismatch(2.2 vs 3.83)"}, "214430": {"naver": true, "eps": "blank", "bps": "ok", "per": "blank", "pbr": "ok"}, "017900": {"naver": true, "eps": "ok", "bps": "ok", "per": "ok", "pbr": "ok"}, "094800": {"naver": false, "eps": "no_naver", "bps": "no_naver", "per": "no_naver", "pbr": "no_naver"}, "005810": {"naver": true, "eps": "ok", "bps": "ok", "per": "ok", "pbr": "ok"}, "452260": {"naver": true, "eps": "ok", "bps": "ok", "per": "ok", "pbr": "ok"}, "161000": {"naver": true, "eps": "ok", "bps": "ok", "per": "ok_unverified", "pbr": "ok"}, "035890": {"naver": true, "eps": "ok", "bps": "ok", "per": "ok", "pbr": "ok"}, "009410": {"naver": true, "eps": "ok", "bps": "ok", "per": "ok", "pbr": "ok"}, "217590": {"naver": true, "eps": "blank", "bps": "ok", "per": "no_naver", "pbr": "ok"}, "278280": {"naver": true, "eps": "mismatch(-5587 vs -6381.0)", "bps": "ok", "per": "ok_unverified", "pbr": "ok"}, "448900": {"naver": true, "eps": "ok", "bps": "ok", "per": "ok_unverified", "pbr": "ok"}, "002240": {"naver": true, "eps": "mismatch(722 vs 924.0)", "bps": "mismatch(77743 vs 69493.0)", "per": "mismatch(26.36 vs 20.6)", "pbr": "mismatch(0.24 vs 0.27)"}, "003300": {"naver": true, "eps": "ok", "bps": "ok", "per": "ok", "pbr": "ok"}, "089010": {"naver": true, "eps": "ok", "bps": "ok", "per": "ok", "pbr": "ok"}, "160980": {"naver": true, "eps": "ok", "bps": "ok", "per": "ok", "pbr": "ok"}, "284740": {"naver": true, "eps": "ok", "bps": "ok", "per": "ok", "pbr": "ok"}, "005250": {"naver": true, "eps": "mismatch(-1252 vs -1812.0)", "bps": "ok", "per": "ok_unverified", "pbr": "ok"}, "368770": {"naver": true, "eps": "ok", "bps": "ok", "per": "ok", "pbr": "ok"}, "475960": {"naver": true, "eps": "ok", "bps": "ok", "per": "ok_unverified", "pbr": "ok"}, "039440": {"naver": true, "eps": "ok", "bps": "ok", "per": "ok", "pbr": "ok"}, "460930": {"naver": true, "eps": "ok", "bps": "ok", "per": "ok", "pbr": "ok"}, "268280": {"naver": true, "eps": "blank", "bps": "ok", "per": "blank", "pbr": "ok"}, "005420": {"naver": true, "eps": "mismatch(-779 vs -671.0)", "bps": "ok", "per": "ok_unverified", "pbr": "ok"}, "125490": {"naver": true, "eps": "blank", "bps": "ok", "per": "blank", "pbr": "ok"}, "219130": {"naver": true, "eps": "blank", "bps": "ok", "per": "blank", "pbr": "ok"}, "377740": {"naver": true, "eps": "ok", "bps": "ok", "per": "ok_unverified", "pbr": "ok"}, "230360": {"naver": true, "eps": "ok", "bps": "ok", "per": "ok", "pbr": "ok"}, "004710": {"naver": true, "eps": "mismatch(-54 vs -499.0)", "bps": "mismatch(9921 vs 10878.0)", "per": "ok_unverified", "pbr": "mismatch(1.22 vs 1.12)"}, "271940": {"naver": true, "eps": "blank", "bps": "ok", "per": "no_naver", "pbr": "ok"}, "200470": {"naver": true, "eps": "blank", "bps": "ok", "per": "blank", "pbr": "ok"}, "020000": {"naver": true, "eps": "ok", "bps": "ok", "per": "ok", "pbr": "ok"}, "211050": {"naver": true, "eps": "ok", "bps": "ok", "per": "ok", "pbr": "ok"}, "001530": {"naver": true, "eps": "ok", "bps": "ok", "per": "ok_unverified", "pbr": "ok"}, "030520": {"naver": true, "eps": "mismatch(1029 vs 1388.0)", "bps": "mismatch(20195 vs 15306.0)", "per": "mismatch(19.34 vs 14.34)", "pbr": "mismatch(0.99 vs 1.3)"}, "110990": {"naver": true, "eps": "ok", "bps": "ok", "per": "ok", "pbr": "ok"}, "019170": {"naver": true, "eps": "ok", "bps": "mismatch(5975 vs 5507.0)", "per": "ok", "pbr": "ok"}, "241770": {"naver": true, "eps": "ok", "bps": "ok", "per": "ok", "pbr": "ok"}, "340570": {"naver": true, "eps": "ok", "bps": "ok", "per": "ok", "pbr": "ok"}, "460860": {"naver": true, "eps": "blank", "bps": "ok", "per": "blank", "pbr": "ok"}, "356680": {"naver": true, "eps": "blank", "bps": "ok", "per": "blank", "pbr": "ok"}, "014830": {"naver": true, "eps": "ok", "bps": "ok", "per": "ok", "pbr": "ok"}, "099190": {"naver": true, "eps": "ok", "bps": "mismatch(14560 vs 11625.0)", "per": "ok_unverified", "pbr": "mismatch(1.12 vs 1.4)"}, "381970": {"naver": true, "eps": "blank", "bps": "ok", "per": "blank", "pbr": "ok"}, "006220": {"naver": true, "eps": "ok", "bps": "ok", "per": "ok", "pbr": "ok"}, "041190": {"naver": true, "eps": "ok", "bps": "ok", "per": "ok", "pbr": "ok"}, "024850": {"naver": true, "eps": "mismatch(-227 vs -1178.0)", "bps": "mismatch(1511 vs 7051.0)", "per": "ok_unverified", "pbr": "mismatch(9.58 vs 2.05)"}, "042000": {"naver": true, "eps": "ok", "bps": "ok", "per": "ok", "pbr": "ok"}, "448730": {"naver": true, "eps": "blank", "bps": "mismatch(1116 vs 4444.0)", "per": "blank", "pbr": "mismatch(4.5 vs 1.13)"}, "251970": {"naver": true, "eps": "blank", "bps": "ok", "per": "blank", "pbr": "ok"}, "114810": {"naver": true, "eps": "ok", "bps": "ok", "per": "ok", "pbr": "ok"}, "016610": {"naver": true, "eps": "ok", "bps": "ok", "per": "ok", "pbr": "ok"}, "001200": {"naver": true, "eps": "ok", "bps": "ok", "per": "ok", "pbr": "ok"}, "145990": {"naver": true, "eps": "ok", "bps": "ok", "per": "ok_unverified", "pbr": "ok"}, "101160": {"naver": true, "eps": "ok", "bps": "ok", "per": "ok", "pbr": "ok"}, "034950": {"naver": true, "eps": "ok", "bps": "ok", "per": "ok", "pbr": "ok"}, "060280": {"naver": true, "eps": "blank", "bps": "ok", "per": "blank", "pbr": "ok"}, "008730": {"naver": true, "eps": "ok", "bps": "ok", "per": "ok_unverified", "pbr": "ok"}, "018290": {"naver": true, "eps": "ok", "bps": "ok", "per": "ok", "pbr": "ok"}, "025980": {"naver": true, "eps": "ok", "bps": "ok", "per": "ok_unverified", "pbr": "ok"}, "034310": {"naver": true, "eps": "ok", "bps": "ok", "per": "ok", "pbr": "ok"}, "009900": {"naver": true, "eps": "ok", "bps": "ok", "per": "ok", "pbr": "ok"}, "393890": {"naver": true, "eps": "ok", "bps": "ok", "per": "ok_unverified", "pbr": "ok"}, "004690": {"naver": true, "eps": "mismatch(34307 vs 30693.0)", "bps": "ok", "per": "mismatch(3.56 vs 3.98)", "pbr": "ok"}, "003000": {"naver": true, "eps": "mismatch(139 vs 153.0)", "bps": "ok", "per": "mismatch(32.19 vs 29.25)", "pbr": "ok"}, "036620": {"naver": true, "eps": "blank", "bps": "ok", "per": "blank", "pbr": "ok"}, "130660": {"naver": true, "eps": "ok", "bps": "ok", "per": "ok", "pbr": "ok"}, "000070": {"naver": true, "eps": "ok", "bps": "ok", "per": "ok_unverified", "pbr": "ok"}, "005950": {"naver": true, "eps": "ok", "bps": "ok", "per": "ok_unverified", "pbr": "ok"}, "144960": {"naver": true, "eps": "blank", "bps": "ok", "per": "blank", "pbr": "ok"}, "372320": {"naver": true, "eps": "blank", "bps": "ok", "per": "no_naver", "pbr": "ok"}, "003280": {"naver": true, "eps": "ok", "bps": "ok", "per": "ok", "pbr": "ok"}, "072710": {"naver": true, "eps": "ok", "bps": "ok", "per": "ok", "pbr": "ok"}, "092190": {"naver": true, "eps": "mismatch(162 vs 123.0)", "bps": "ok", "per": "mismatch(58.15 vs 76.59)", "pbr": "ok"}, "078350": {"naver": true, "eps": "ok", "bps": "ok", "per": "ok", "pbr": "ok"}, "011930": {"naver": true, "eps": "mismatch(-15 vs -152.0)", "bps": "mismatch(1106 vs 11179.0)", "per": "ok_unverified", "pbr": "mismatch(18.85 vs 1.87)"}, "095660": {"naver": true, "eps": "ok", "bps": "ok", "per": "mismatch(7.94 vs 7.34)", "pbr": "ok"}, "290550": {"naver": true, "eps": "ok", "bps": "ok", "per": "ok", "pbr": "ok"}, "079940": {"naver": true, "eps": "ok", "bps": "ok", "per": "ok", "pbr": "ok"}, "403550": {"naver": true, "eps": "ok", "bps": "ok", "per": "ok_unverified", "pbr": "ok"}, "029530": {"naver": true, "eps": "ok", "bps": "ok", "per": "ok", "pbr": "ok"}, "215200": {"naver": true, "eps": "ok", "bps": "ok", "per": "ok", "pbr": "ok"}, "950210": {"naver": true, "eps": "blank", "bps": "blank", "per": "no_naver", "pbr": "blank"}, "015360": {"naver": true, "eps": "mismatch(22768 vs 4250.0)", "bps": "mismatch(125418 vs 30797.0)", "per": "mismatch(0.67 vs 3.61)", "pbr": "mismatch(0.12 vs 0.5)"}, "060980": {"naver": true, "eps": "ok", "bps": "ok", "per": "ok", "pbr": "ok"}, "078130": {"naver": true, "eps": "blank", "bps": "mismatch(106 vs 1061.0)", "per": "no_naver", "pbr": "mismatch(34.91 vs 3.49)"}, "389500": {"naver": true, "eps": "blank", "bps": "ok", "per": "no_naver", "pbr": "ok"}, "101930": {"naver": true, "eps": "mismatch(3756 vs 742.0)", "bps": "mismatch(36984 vs 7439.0)", "per": "mismatch(2.4 vs 12.16)", "pbr": "mismatch(0.24 vs 1.21)"}, "004700": {"naver": true, "eps": "blank", "bps": "mismatch(87597 vs 163935.0)", "per": "blank", "pbr": "mismatch(0.71 vs 0.38)"}, "0011T0": {"naver": true, "eps": "blank", "bps": "blank", "per": "no_naver", "pbr": "blank"}, "425040": {"naver": true, "eps": "ok", "bps": "mismatch(10782 vs 9407.0)", "per": "ok", "pbr": "mismatch(1.8 vs 2.06)"}, "493280": {"naver": true, "eps": "blank", "bps": "ok", "per": "blank", "pbr": "ok"}, "016590": {"naver": true, "eps": "ok", "bps": "mismatch(23605 vs 20442.0)", "per": "ok", "pbr": "mismatch(0.43 vs 0.5)"}, "417310": {"naver": true, "eps": "blank", "bps": "ok", "per": "blank", "pbr": "ok"}, "025320": {"naver": true, "eps": "ok", "bps": "ok", "per": "mismatch(94.89 vs 87.45)", "pbr": "ok"}, "025900": {"naver": true, "eps": "ok", "bps": "ok", "per": "ok_unverified", "pbr": "ok"}, "002030": {"naver": true, "eps": "ok", "bps": "ok", "per": "ok", "pbr": "ok"}, "006910": {"naver": true, "eps": "blank", "bps": "ok", "per": "blank", "pbr": "ok"}, "192650": {"naver": true, "eps": "mismatch(-82 vs -112.0)", "bps": "mismatch(8001 vs 5522.0)", "per": "ok_unverified", "pbr": "mismatch(0.73 vs 1.06)"}, "013030": {"naver": true, "eps": "ok", "bps": "ok", "per": "ok", "pbr": "ok"}, "138080": {"naver": true, "eps": "mismatch(-1597 vs -1758.0)", "bps": "ok", "per": "ok_unverified", "pbr": "ok"}, "199800": {"naver": true, "eps": "blank", "bps": "ok", "per": "no_naver", "pbr": "ok"}, "064260": {"naver": true, "eps": "ok", "bps": "mismatch(4862 vs 4105.0)", "per": "ok_unverified", "pbr": "mismatch(1.09 vs 1.3)"}, "092870": {"naver": true, "eps": "ok", "bps": "ok", "per": "ok", "pbr": "ok"}, "306200": {"naver": true, "eps": "ok", "bps": "ok", "per": "ok", "pbr": "ok"}, "078160": {"naver": true, "eps": "ok", "bps": "ok", "per": "ok_unverified", "pbr": "ok"}, "002810": {"naver": true, "eps": "ok", "bps": "ok", "per": "ok", "pbr": "ok"}, "085910": {"naver": true, "eps": "ok", "bps": "ok", "per": "ok", "pbr": "ok"}, "357120": {"naver": true, "eps": "blank", "bps": "mismatch(2468 vs 4815.0)", "per": "blank", "pbr": "mismatch(1.66 vs 0.85)"}, "052710": {"naver": true, "eps": "ok", "bps": "ok", "per": "ok", "pbr": "ok"}, "417840": {"naver": true, "eps": "mismatch(899 vs 301.0)", "bps": "mismatch(8842 vs 2836.0)", "per": "mismatch(19.47 vs 58.14)", "pbr": "mismatch(1.98 vs 6.17)"}, "012030": {"naver": true, "eps": "ok", "bps": "ok", "per": "ok", "pbr": "ok"}, "080580": {"naver": true, "eps": "ok", "bps": "ok", "per": "ok", "pbr": "ok"}, "145720": {"naver": true, "eps": "mismatch(2434 vs 1933.0)", "bps": "ok", "per": "mismatch(18.76 vs 23.62)", "pbr": "ok"}, "027410": {"naver": true, "eps": "ok", "bps": "ok", "per": "ok", "pbr": "mismatch(0.2 vs 0.22)"}, "304360": {"naver": true, "eps": "ok", "bps": "ok", "per": "ok_unverified", "pbr": "ok"}, "065680": {"naver": true, "eps": "ok", "bps": "ok", "per": "ok", "pbr": "ok"}, "394280": {"naver": true, "eps": "ok", "bps": "ok", "per": "ok_unverified", "pbr": "ok"}, "092200": {"naver": true, "eps": "mismatch(-175 vs -324.0)", "bps": "ok", "per": "ok_unverified", "pbr": "ok"}, "107640": {"naver": true, "eps": "ok", "bps": "ok", "per": "ok", "pbr": "ok"}, "424870": {"naver": true, "eps": "blank", "bps": "ok", "per": "no_naver", "pbr": "ok"}, "455900": {"naver": true, "eps": "blank", "bps": "ok", "per": "no_naver", "pbr": "ok"}, "017810": {"naver": true, "eps": "mismatch(598 vs 691.0)", "bps": "ok", "per": "mismatch(16.82 vs 14.56)", "pbr": "ok"}, "036200": {"naver": true, "eps": "blank", "bps": "ok", "per": "blank", "pbr": "ok"}, "265520": {"naver": true, "eps": "ok", "bps": "ok", "per": "ok", "pbr": "ok"}, "482630": {"naver": true, "eps": "blank", "bps": "mismatch(11409 vs 5705.0)", "per": "blank", "pbr": "mismatch(1.53 vs 3.05)"}, "010820": {"naver": true, "eps": "blank", "bps": "ok", "per": "blank", "pbr": "ok"}, "452280": {"naver": true, "eps": "blank", "bps": "ok", "per": "blank", "pbr": "ok"}, "0120G0": {"naver": true, "eps": "blank", "bps": "blank", "per": "blank", "pbr": "blank"}, "468530": {"naver": true, "eps": "blank", "bps": "ok", "per": "no_naver", "pbr": "ok"}, "079370": {"naver": true, "eps": "mismatch(-314 vs -358.0)", "bps": "ok", "per": "ok_unverified", "pbr": "ok"}, "117730": {"naver": true, "eps": "mismatch(-1743 vs -1918.0)", "bps": "ok", "per": "ok_unverified", "pbr": "ok"}, "067630": {"naver": true, "eps": "ok", "bps": "ok", "per": "ok_unverified", "pbr": "ok"}, "092790": {"naver": true, "eps": "ok", "bps": "ok", "per": "ok", "pbr": "ok"}, "254490": {"naver": true, "eps": "blank", "bps": "ok", "per": "blank", "pbr": "ok"}, "097520": {"naver": true, "eps": "ok", "bps": "ok", "per": "ok", "pbr": "ok"}, "344820": {"naver": true, "eps": "ok", "bps": "ok", "per": "ok_unverified", "pbr": "ok"}, "029460": {"naver": true, "eps": "ok", "bps": "ok", "per": "ok", "pbr": "ok"}, "078020": {"naver": true, "eps": "blank", "bps": "mismatch(13046 vs 15566.0)", "per": "blank", "pbr": "mismatch(0.51 vs 0.43)"}, "332570": {"naver": true, "eps": "ok", "bps": "ok", "per": "ok", "pbr": "ok"}, "354320": {"naver": true, "eps": "ok", "bps": "mismatch(29761 vs 24158.0)", "per": "ok", "pbr": "mismatch(1.93 vs 2.38)"}, "105840": {"naver": true, "eps": "ok", "bps": "ok", "per": "ok", "pbr": "ok"}, "183190": {"naver": true, "eps": "ok", "bps": "ok", "per": "ok", "pbr": "ok"}, "042520": {"naver": true, "eps": "blank", "bps": "mismatch(2594 vs 5204.0)", "per": "no_naver", "pbr": "mismatch(9.79 vs 4.88)"}, "119850": {"naver": true, "eps": "ok", "bps": "ok", "per": "ok", "pbr": "ok"}, "003800": {"naver": true, "eps": "ok", "bps": "ok", "per": "ok", "pbr": "ok"}, "010690": {"naver": true, "eps": "ok", "bps": "ok", "per": "ok", "pbr": "ok"}, "047920": {"naver": true, "eps": "blank", "bps": "ok", "per": "blank", "pbr": "ok"}, "170900": {"naver": true, "eps": "mismatch(-1343 vs -1199.0)", "bps": "mismatch(74748 vs 67799.0)", "per": "ok_unverified", "pbr": "mismatch(0.49 vs 0.54)"}, "069540": {"naver": true, "eps": "blank", "bps": "ok", "per": "no_naver", "pbr": "ok"}, "389650": {"naver": true, "eps": "blank", "bps": "ok", "per": "no_naver", "pbr": "ok"}, "215600": {"naver": true, "eps": "blank", "bps": "ok", "per": "no_naver", "pbr": "ok"}, "098070": {"naver": true, "eps": "blank", "bps": "ok", "per": "blank", "pbr": "ok"}, "243070": {"naver": true, "eps": "ok", "bps": "mismatch(56347 vs 31800.0)", "per": "ok", "pbr": "mismatch(0.52 vs 0.93)"}, "005610": {"naver": true, "eps": "ok", "bps": "ok", "per": "ok_unverified", "pbr": "ok"}, "230240": {"naver": true, "eps": "ok", "bps": "ok", "per": "ok_unverified", "pbr": "ok"}, "179900": {"naver": true, "eps": "ok", "bps": "ok", "per": "ok_unverified", "pbr": "ok"}, "086390": {"naver": true, "eps": "ok", "bps": "ok", "per": "ok_unverified", "pbr": "ok"}, "089590": {"naver": true, "eps": "ok", "bps": "ok", "per": "ok_unverified", "pbr": "ok"}, "092230": {"naver": true, "eps": "ok", "bps": "ok", "per": "ok", "pbr": "ok"}, "187660": {"naver": true, "eps": "blank", "bps": "ok", "per": "no_naver", "pbr": "ok"}, "105630": {"naver": true, "eps": "ok", "bps": "ok", "per": "ok", "pbr": "ok"}, "206650": {"naver": true, "eps": "blank", "bps": "ok", "per": "blank", "pbr": "ok"}, "084110": {"naver": true, "eps": "ok", "bps": "ok", "per": "ok", "pbr": "ok"}, "015860": {"naver": true, "eps": "ok", "bps": "ok", "per": "ok", "pbr": "ok"}, "488900": {"naver": true, "eps": "blank", "bps": "ok", "per": "no_naver", "pbr": "ok"}, "126720": {"naver": true, "eps": "ok", "bps": "ok", "per": "ok", "pbr": "ok"}, "126560": {"naver": true, "eps": "ok", "bps": "ok", "per": "ok", "pbr": "ok"}, "002710": {"naver": true, "eps": "ok", "bps": "ok", "per": "ok_unverified", "pbr": "ok"}, "376270": {"naver": true, "eps": "ok", "bps": "ok", "per": "ok_unverified", "pbr": "ok"}, "036890": {"naver": true, "eps": "ok", "bps": "ok", "per": "ok", "pbr": "ok"}, "069080": {"naver": true, "eps": "mismatch(1005 vs 912.0)", "bps": "ok", "per": "mismatch(10.87 vs 11.97)", "pbr": "ok"}, "058430": {"naver": true, "eps": "mismatch(2398 vs 240.0)", "bps": "mismatch(64117 vs 6412.0)", "per": "mismatch(2.34 vs 23.38)", "pbr": "mismatch(0.09 vs 0.87)"}, "287840": {"naver": true, "eps": "blank", "bps": "ok", "per": "no_naver", "pbr": "ok"}, "194370": {"naver": true, "eps": "ok", "bps": "ok", "per": "ok", "pbr": "ok"}, "049070": {"naver": true, "eps": "mismatch(904 vs 1272.0)", "bps": "ok", "per": "mismatch(21.37 vs 15.19)", "pbr": "ok"}, "200880": {"naver": true, "eps": "ok", "bps": "ok", "per": "ok", "pbr": "ok"}, "477850": {"naver": true, "eps": "blank", "bps": "ok", "per": "no_naver", "pbr": "ok"}, "456010": {"naver": true, "eps": "ok", "bps": "ok", "per": "ok_unverified", "pbr": "ok"}, "462350": {"naver": true, "eps": "ok", "bps": "mismatch(1989 vs 1673.0)", "per": "ok_unverified", "pbr": "mismatch(7.94 vs 9.44)"}, "001940": {"naver": true, "eps": "ok", "bps": "ok", "per": "ok_unverified", "pbr": "ok"}, "011760": {"naver": true, "eps": "ok", "bps": "ok", "per": "ok", "pbr": "ok"}, "005720": {"naver": true, "eps": "ok", "bps": "ok", "per": "ok", "pbr": "ok"}, "234340": {"naver": true, "eps": "ok", "bps": "mismatch(13897 vs 12723.0)", "per": "ok", "pbr": "mismatch(1.68 vs 1.84)"}, "484590": {"naver": true, "eps": "blank", "bps": "ok", "per": "blank", "pbr": "ok"}, "091810": {"naver": true, "eps": "mismatch(-751 vs -1074.0)", "bps": "mismatch(334 vs 261.0)", "per": "ok_unverified", "pbr": "mismatch(2.36 vs 3.02)"}, "091700": {"naver": true, "eps": "ok", "bps": "ok", "per": "ok", "pbr": "ok"}, "232530": {"naver": false, "eps": "no_naver", "bps": "no_naver", "per": "no_naver", "pbr": "no_naver"}, "204620": {"naver": true, "eps": "ok", "bps": "ok", "per": "ok", "pbr": "ok"}, "187870": {"naver": true, "eps": "mismatch(4020 vs 2054.0)", "bps": "mismatch(23285 vs 12465.0)", "per": "mismatch(5.87 vs 11.49)", "pbr": "mismatch(1.01 vs 1.89)"}, "317330": {"naver": true, "eps": "ok", "bps": "ok", "per": "ok_unverified", "pbr": "ok"}, "445090": {"naver": true, "eps": "ok", "bps": "ok", "per": "ok_unverified", "pbr": "ok"}, "441270": {"naver": true, "eps": "mismatch(-199 vs -230.0)", "bps": "ok", "per": "ok_unverified", "pbr": "ok"}, "018250": {"naver": true, "eps": "blank", "bps": "ok", "per": "blank", "pbr": "ok"}, "104700": {"naver": true, "eps": "blank", "bps": "mismatch(20430 vs 23535.0)", "per": "no_naver", "pbr": "mismatch(0.43 vs 0.37)"}, "200670": {"naver": true, "eps": "blank", "bps": "ok", "per": "blank", "pbr": "ok"}, "009290": {"naver": true, "eps": "ok", "bps": "ok", "per": "ok", "pbr": "ok"}, "001390": {"naver": true, "eps": "ok", "bps": "ok", "per": "ok", "pbr": "ok"}, "092460": {"naver": true, "eps": "ok", "bps": "ok", "per": "ok", "pbr": "ok"}, "034830": {"naver": true, "eps": "ok", "bps": "ok", "per": "mismatch(15.26 vs 14.06)", "pbr": "ok"}, "064820": {"naver": true, "eps": "ok", "bps": "ok", "per": "ok", "pbr": "ok"}, "025860": {"naver": true, "eps": "mismatch(226 vs 258.0)", "bps": "ok", "per": "mismatch(28.1 vs 24.61)", "pbr": "ok"}, "000430": {"naver": true, "eps": "ok", "bps": "ok", "per": "ok", "pbr": "ok"}, "002310": {"naver": true, "eps": "ok", "bps": "ok", "per": "ok", "pbr": "ok"}, "228760": {"naver": true, "eps": "ok", "bps": "ok", "per": "ok_unverified", "pbr": "ok"}, "094360": {"naver": true, "eps": "blank", "bps": "ok", "per": "blank", "pbr": "ok"}, "452430": {"naver": true, "eps": "blank", "bps": "ok", "per": "no_naver", "pbr": "ok"}, "272110": {"naver": true, "eps": "ok", "bps": "ok", "per": "ok", "pbr": "ok"}, "475400": {"naver": true, "eps": "ok", "bps": "ok", "per": "ok_unverified", "pbr": "ok"}, "016800": {"naver": true, "eps": "ok", "bps": "ok", "per": "ok", "pbr": "ok"}, "078340": {"naver": true, "eps": "mismatch(-37 vs 1478.0)", "bps": "mismatch(114052 vs 84820.0)", "per": "mismatch(-687.84 vs 17.22)", "pbr": "mismatch(0.22 vs 0.3)"}, "061970": {"naver": true, "eps": "ok", "bps": "ok", "per": "ok_unverified", "pbr": "ok"}, "084690": {"naver": true, "eps": "ok", "bps": "ok", "per": "ok_unverified", "pbr": "ok"}, "314930": {"naver": true, "eps": "blank", "bps": "ok", "per": "blank", "pbr": "ok"}, "236200": {"naver": true, "eps": "ok", "bps": "ok", "per": "ok", "pbr": "ok"}, "203650": {"naver": true, "eps": "mismatch(72 vs 80.0)", "bps": "mismatch(3042 vs 1253.0)", "per": "mismatch(41.53 vs 37.38)", "pbr": "mismatch(0.98 vs 2.39)"}, "136480": {"naver": true, "eps": "ok", "bps": "ok", "per": "ok", "pbr": "ok"}, "084010": {"naver": true, "eps": "mismatch(315 vs 232.0)", "bps": "mismatch(51579 vs 27618.0)", "per": "mismatch(27.87 vs 37.84)", "pbr": "mismatch(0.17 vs 0.32)"}, "378340": {"naver": true, "eps": "blank", "bps": "ok", "per": "no_naver", "pbr": "ok"}, "286940": {"naver": true, "eps": "mismatch(313 vs 752.0)", "bps": "mismatch(41074 vs 28022.0)", "per": "mismatch(63.42 vs 26.4)", "pbr": "mismatch(0.48 vs 0.71)"}, "241520": {"naver": true, "eps": "ok", "bps": "ok", "per": "ok", "pbr": "ok"}, "108670": {"naver": true, "eps": "ok", "bps": "ok", "per": "ok_unverified", "pbr": "ok"}, "089980": {"naver": true, "eps": "ok", "bps": "ok", "per": "ok", "pbr": "ok"}, "007690": {"naver": true, "eps": "ok", "bps": "ok", "per": "ok", "pbr": "ok"}, "009160": {"naver": true, "eps": "mismatch(282 vs 246.0)", "bps": "mismatch(13168 vs 11930.0)", "per": "mismatch(16.01 vs 18.35)", "pbr": "mismatch(0.34 vs 0.38)"}, "033270": {"naver": true, "eps": "blank", "bps": "ok", "per": "blank", "pbr": "ok"}, "042370": {"naver": true, "eps": "blank", "bps": "ok", "per": "blank", "pbr": "ok"}, "043150": {"naver": true, "eps": "ok", "bps": "ok", "per": "ok", "pbr": "ok"}, "025770": {"naver": true, "eps": "ok", "bps": "ok", "per": "ok", "pbr": "ok"}, "159010": {"naver": true, "eps": "blank", "bps": "ok", "per": "no_naver", "pbr": "ok"}, "001750": {"naver": true, "eps": "blank", "bps": "mismatch(48876 vs 44072.0)", "per": "blank", "pbr": "mismatch(0.47 vs 0.52)"}, "036800": {"naver": true, "eps": "ok", "bps": "ok", "per": "ok", "pbr": "ok"}, "322310": {"naver": true, "eps": "blank", "bps": "ok", "per": "no_naver", "pbr": "ok"}, "151860": {"naver": true, "eps": "ok", "bps": "ok", "per": "ok", "pbr": "ok"}, "272450": {"naver": true, "eps": "blank", "bps": "ok", "per": "no_naver", "pbr": "ok"}, "001230": {"naver": true, "eps": "mismatch(647 vs 129.0)", "bps": "mismatch(58289 vs 14614.0)", "per": "mismatch(2.85 vs 14.31)", "pbr": "mismatch(0.03 vs 0.13)"}, "003720": {"naver": true, "eps": "blank", "bps": "ok", "per": "blank", "pbr": "ok"}, "099430": {"naver": true, "eps": "ok", "bps": "ok", "per": "ok", "pbr": "ok"}, "035810": {"naver": true, "eps": "ok", "bps": "ok", "per": "ok", "pbr": "ok"}, "274090": {"naver": true, "eps": "ok", "bps": "ok", "per": "ok_unverified", "pbr": "ok"}, "096760": {"naver": true, "eps": "ok", "bps": "ok", "per": "ok", "pbr": "ok"}, "101730": {"naver": true, "eps": "ok", "bps": "ok", "per": "ok_unverified", "pbr": "ok"}, "046970": {"naver": true, "eps": "ok", "bps": "ok", "per": "ok", "pbr": "ok"}, "037710": {"naver": true, "eps": "blank", "bps": "ok", "per": "blank", "pbr": "ok"}, "017390": {"naver": true, "eps": "ok", "bps": "ok", "per": "ok", "pbr": "ok"}, "024720": {"naver": true, "eps": "mismatch(1125 vs 1484.0)", "bps": "ok", "per": "mismatch(7.3 vs 5.53)", "pbr": "ok"}, "450950": {"naver": true, "eps": "blank", "bps": "ok", "per": "blank", "pbr": "ok"}, "051500": {"naver": true, "eps": "ok", "bps": "ok", "per": "ok", "pbr": "ok"}, "001340": {"naver": true, "eps": "ok", "bps": "ok", "per": "ok", "pbr": "ok"}, "123890": {"naver": true, "eps": "ok", "bps": "ok", "per": "ok", "pbr": "ok"}, "064850": {"naver": true, "eps": "ok", "bps": "ok", "per": "ok", "pbr": "ok"}, "900140": {"naver": true, "eps": "blank", "bps": "blank", "per": "blank", "pbr": "blank"}, "035600": {"naver": true, "eps": "ok", "bps": "ok", "per": "ok", "pbr": "ok"}, "298830": {"naver": true, "eps": "ok", "bps": "ok", "per": "ok", "pbr": "ok"}, "000650": {"naver": true, "eps": "blank", "bps": "ok", "per": "no_naver", "pbr": "ok"}, "078520": {"naver": true, "eps": "ok", "bps": "ok", "per": "ok", "pbr": "ok"}, "005430": {"naver": true, "eps": "ok", "bps": "ok", "per": "ok", "pbr": "ok"}, "112290": {"naver": true, "eps": "blank", "bps": "ok", "per": "blank", "pbr": "ok"}, "242040": {"naver": true, "eps": "mismatch(-12 vs -39.0)", "bps": "ok", "per": "ok_unverified", "pbr": "ok"}, "092730": {"naver": true, "eps": "ok", "bps": "ok", "per": "ok", "pbr": "ok"}, "026890": {"naver": true, "eps": "ok", "bps": "ok", "per": "ok", "pbr": "ok"}, "078150": {"naver": true, "eps": "ok", "bps": "ok", "per": "ok", "pbr": "ok"}, "200130": {"naver": true, "eps": "ok", "bps": "ok", "per": "ok_unverified", "pbr": "ok"}, "060720": {"naver": true, "eps": "ok", "bps": "ok", "per": "ok", "pbr": "ok"}, "309710": {"naver": true, "eps": "blank", "bps": "ok", "per": "no_naver", "pbr": "ok"}, "054950": {"naver": true, "eps": "ok", "bps": "ok", "per": "ok", "pbr": "ok"}, "002900": {"naver": true, "eps": "ok", "bps": "ok", "per": "ok", "pbr": "ok"}, "0001A0": {"naver": true, "eps": "blank", "bps": "blank", "per": "blank", "pbr": "blank"}, "215000": {"naver": true, "eps": "mismatch(1283 vs 3354.0)", "bps": "mismatch(80906 vs 71930.0)", "per": "mismatch(33.16 vs 12.69)", "pbr": "mismatch(0.53 vs 0.59)"}, "023410": {"naver": true, "eps": "ok", "bps": "ok", "per": "ok", "pbr": "ok"}, "005680": {"naver": true, "eps": "ok", "bps": "ok", "per": "ok", "pbr": "ok"}, "036170": {"naver": true, "eps": "blank", "bps": "ok", "per": "blank", "pbr": "ok"}, "073490": {"naver": true, "eps": "ok", "bps": "ok", "per": "ok", "pbr": "ok"}, "144510": {"naver": true, "eps": "ok", "bps": "ok", "per": "ok_unverified", "pbr": "ok"}, "017860": {"naver": true, "eps": "ok", "bps": "ok", "per": "ok_unverified", "pbr": "ok"}, "003120": {"naver": true, "eps": "blank", "bps": "mismatch(28490 vs 52907.0)", "per": "blank", "pbr": "mismatch(0.7 vs 0.38)"}, "182400": {"naver": true, "eps": "mismatch(-113 vs -144.0)", "bps": "mismatch(119 vs 85.0)", "per": "ok_unverified", "pbr": "mismatch(30.84 vs 43.18)"}, "058970": {"naver": true, "eps": "mismatch(-74 vs -53.0)", "bps": "ok", "per": "ok_unverified", "pbr": "ok"}, "114190": {"naver": true, "eps": "blank", "bps": "ok", "per": "no_naver", "pbr": "ok"}, "365270": {"naver": true, "eps": "blank", "bps": "ok", "per": "no_naver", "pbr": "ok"}, "448280": {"naver": true, "eps": "ok", "bps": "ok", "per": "ok", "pbr": "ok"}, "194700": {"naver": true, "eps": "ok", "bps": "ok", "per": "ok", "pbr": "ok"}, "355150": {"naver": true, "eps": "blank", "bps": "ok", "per": "blank", "pbr": "ok"}, "472850": {"naver": true, "eps": "ok", "bps": "ok", "per": "ok", "pbr": "ok"}, "108860": {"naver": true, "eps": "mismatch(-143 vs -179.0)", "bps": "ok", "per": "ok_unverified", "pbr": "ok"}, "043370": {"naver": true, "eps": "ok", "bps": "ok", "per": "ok", "pbr": "ok"}, "051360": {"naver": true, "eps": "ok", "bps": "ok", "per": "ok", "pbr": "ok"}, "011500": {"naver": true, "eps": "blank", "bps": "ok", "per": "blank", "pbr": "ok"}, "003920": {"naver": true, "eps": "ok", "bps": "ok", "per": "ok", "pbr": "ok"}, "251370": {"naver": true, "eps": "mismatch(170 vs -8.0)", "bps": "ok", "per": "ok_unverified", "pbr": "ok"}, "005010": {"naver": true, "eps": "ok", "bps": "ok", "per": "ok_unverified", "pbr": "ok"}, "053030": {"naver": true, "eps": "ok", "bps": "ok", "per": "ok_unverified", "pbr": "ok"}, "267980": {"naver": true, "eps": "ok", "bps": "ok", "per": "ok", "pbr": "ok"}, "419530": {"naver": true, "eps": "ok", "bps": "ok", "per": "ok", "pbr": "ok"}, "122900": {"naver": true, "eps": "ok", "bps": "ok", "per": "ok", "pbr": "ok"}, "900290": {"naver": true, "eps": "blank", "bps": "mismatch(59 vs 13517.0)", "per": "blank", "pbr": "mismatch(53.56 vs 0.23)"}, "0082N0": {"naver": true, "eps": "blank", "bps": "blank", "per": "no_naver", "pbr": "blank"}, "002320": {"naver": true, "eps": "mismatch(-117 vs -225.0)", "bps": "mismatch(125789 vs 92880.0)", "per": "ok_unverified", "pbr": "mismatch(0.13 vs 0.18)"}, "005500": {"naver": true, "eps": "blank", "bps": "ok", "per": "blank", "pbr": "ok"}, "065660": {"naver": true, "eps": "blank", "bps": "ok", "per": "no_naver", "pbr": "ok"}, "352480": {"naver": true, "eps": "blank", "bps": "ok", "per": "blank", "pbr": "ok"}, "950170": {"naver": true, "eps": "blank", "bps": "mismatch(367 vs 3321.0)", "per": "blank", "pbr": "mismatch(13.5 vs 1.49)"}, "121800": {"naver": true, "eps": "ok", "bps": "ok", "per": "ok_unverified", "pbr": "ok"}, "404990": {"naver": true, "eps": "blank", "bps": "ok", "per": "no_naver", "pbr": "ok"}, "004360": {"naver": true, "eps": "ok", "bps": "ok", "per": "ok", "pbr": "ok"}, "220100": {"naver": true, "eps": "ok", "bps": "ok", "per": "ok_unverified", "pbr": "ok"}, "017890": {"naver": true, "eps": "ok", "bps": "mismatch(36369 vs 27053.0)", "per": "ok", "pbr": "mismatch(0.33 vs 0.44)"}, "377460": {"naver": true, "eps": "blank", "bps": "ok", "per": "blank", "pbr": "ok"}, "036710": {"naver": true, "eps": "mismatch(-188 vs -344.0)", "bps": "mismatch(318 vs 291.0)", "per": "ok_unverified", "pbr": "mismatch(15.06 vs 16.46)"}, "217730": {"naver": true, "eps": "blank", "bps": "ok", "per": "no_naver", "pbr": "ok"}, "004430": {"naver": true, "eps": "ok", "bps": "ok", "per": "ok", "pbr": "ok"}, "084850": {"naver": true, "eps": "ok", "bps": "ok", "per": "ok_unverified", "pbr": "ok"}, "037270": {"naver": true, "eps": "ok", "bps": "ok", "per": "ok", "pbr": "ok"}, "478340": {"naver": true, "eps": "blank", "bps": "ok", "per": "no_naver", "pbr": "ok"}, "003200": {"naver": true, "eps": "ok", "bps": "ok", "per": "ok", "pbr": "ok"}, "098120": {"naver": true, "eps": "ok", "bps": "ok", "per": "ok", "pbr": "ok"}, "389260": {"naver": true, "eps": "ok", "bps": "ok", "per": "ok", "pbr": "ok"}, "0008Z0": {"naver": true, "eps": "blank", "bps": "blank", "per": "blank", "pbr": "blank"}, "014940": {"naver": true, "eps": "ok", "bps": "ok", "per": "ok", "pbr": "ok"}, "416180": {"naver": true, "eps": "ok", "bps": "ok", "per": "ok_unverified", "pbr": "ok"}, "000680": {"naver": true, "eps": "mismatch(-73 vs -179.0)", "bps": "ok", "per": "ok_unverified", "pbr": "ok"}, "180400": {"naver": true, "eps": "mismatch(-285 vs -456.0)", "bps": "ok", "per": "ok_unverified", "pbr": "ok"}, "041920": {"naver": true, "eps": "ok", "bps": "ok", "per": "ok", "pbr": "ok"}, "0030R0": {"naver": true, "eps": "blank", "bps": "blank", "per": "blank", "pbr": "blank"}, "307180": {"naver": true, "eps": "ok", "bps": "mismatch(1329 vs 932.0)", "per": "ok_unverified", "pbr": "mismatch(5.03 vs 7.18)"}, "018000": {"naver": true, "eps": "mismatch(-89 vs -105.0)", "bps": "ok", "per": "ok_unverified", "pbr": "ok"}, "001250": {"naver": true, "eps": "mismatch(118 vs 211.0)", "bps": "mismatch(9465 vs 6715.0)", "per": "mismatch(25.25 vs 14.12)", "pbr": "mismatch(0.31 vs 0.44)"}, "082800": {"naver": true, "eps": "mismatch(-563 vs -636.0)", "bps": "mismatch(1863 vs 1624.0)", "per": "ok_unverified", "pbr": "mismatch(2.17 vs 2.49)"}, "065710": {"naver": true, "eps": "ok", "bps": "ok", "per": "ok", "pbr": "ok"}, "290690": {"naver": true, "eps": "blank", "bps": "ok", "per": "no_naver", "pbr": "ok"}, "318060": {"naver": true, "eps": "blank", "bps": "ok", "per": "no_naver", "pbr": "ok"}, "334890": {"naver": true, "eps": "blank", "bps": "mismatch(3690 vs 6469.0)", "per": "blank", "pbr": "mismatch(0.95 vs 0.54)"}, "459510": {"naver": true, "eps": "blank", "bps": "ok", "per": "no_naver", "pbr": "ok"}, "094480": {"naver": true, "eps": "ok", "bps": "ok", "per": "ok", "pbr": "ok"}, "091580": {"naver": true, "eps": "blank", "bps": "ok", "per": "blank", "pbr": "ok"}, "061090": {"naver": true, "eps": "blank", "bps": "ok", "per": "blank", "pbr": "ok"}, "314130": {"naver": true, "eps": "mismatch(-127 vs -142.0)", "bps": "mismatch(3024 vs 2363.0)", "per": "ok_unverified", "pbr": "mismatch(1.79 vs 2.29)"}, "357550": {"naver": true, "eps": "blank", "bps": "ok", "per": "blank", "pbr": "ok"}, "011560": {"naver": true, "eps": "ok", "bps": "ok", "per": "ok", "pbr": "ok"}, "093520": {"naver": true, "eps": "ok", "bps": "ok", "per": "ok", "pbr": "ok"}, "243840": {"naver": true, "eps": "blank", "bps": "mismatch(9462 vs 8049.0)", "per": "blank", "pbr": "mismatch(0.66 vs 0.78)"}, "046120": {"naver": true, "eps": "blank", "bps": "ok", "per": "blank", "pbr": "ok"}, "025560": {"naver": true, "eps": "ok", "bps": "ok", "per": "ok", "pbr": "ok"}, "446540": {"naver": true, "eps": "blank", "bps": "ok", "per": "blank", "pbr": "ok"}, "475560": {"naver": true, "eps": "blank", "bps": "ok", "per": "no_naver", "pbr": "ok"}, "125020": {"naver": true, "eps": "blank", "bps": "ok", "per": "blank", "pbr": "ok"}, "382900": {"naver": true, "eps": "mismatch(-53 vs -7.0)", "bps": "ok", "per": "ok_unverified", "pbr": "ok"}, "439090": {"naver": true, "eps": "blank", "bps": "ok", "per": "blank", "pbr": "ok"}, "308430": {"naver": true, "eps": "blank", "bps": "ok", "per": "no_naver", "pbr": "ok"}, "023760": {"naver": true, "eps": "blank", "bps": "ok", "per": "blank", "pbr": "ok"}, "003960": {"naver": true, "eps": "ok", "bps": "ok", "per": "ok_unverified", "pbr": "ok"}, "003070": {"naver": true, "eps": "mismatch(-5530 vs -6608.0)", "bps": "ok", "per": "ok_unverified", "pbr": "ok"}, "388790": {"naver": true, "eps": "blank", "bps": "ok", "per": "no_naver", "pbr": "ok"}, "000540": {"naver": true, "eps": "blank", "bps": "ok", "per": "blank", "pbr": "ok"}, "000320": {"naver": true, "eps": "ok", "bps": "ok", "per": "ok", "pbr": "ok"}, "128820": {"naver": true, "eps": "ok", "bps": "ok", "per": "ok_unverified", "pbr": "ok"}, "348950": {"naver": true, "eps": "blank", "bps": "ok", "per": "blank", "pbr": "ok"}, "019010": {"naver": true, "eps": "ok", "bps": "ok", "per": "ok", "pbr": "ok"}, "190510": {"naver": true, "eps": "ok", "bps": "ok", "per": "ok", "pbr": "ok"}, "001460": {"naver": true, "eps": "ok", "bps": "ok", "per": "ok", "pbr": "ok"}, "003520": {"naver": true, "eps": "blank", "bps": "ok", "per": "no_naver", "pbr": "ok"}, "034120": {"naver": true, "eps": "ok", "bps": "ok", "per": "ok", "pbr": "ok"}, "000490": {"naver": true, "eps": "mismatch(-944 vs -1241.0)", "bps": "ok", "per": "ok_unverified", "pbr": "ok"}, "474650": {"naver": true, "eps": "blank", "bps": "ok", "per": "no_naver", "pbr": "ok"}, "095500": {"naver": true, "eps": "ok", "bps": "ok", "per": "ok", "pbr": "ok"}, "010580": {"naver": true, "eps": "blank", "bps": "ok", "per": "blank", "pbr": "ok"}, "012860": {"naver": true, "eps": "ok", "bps": "ok", "per": "ok", "pbr": "ok"}, "100120": {"naver": true, "eps": "ok", "bps": "ok", "per": "ok", "pbr": "ok"}, "000050": {"naver": true, "eps": "ok", "bps": "ok", "per": "ok", "pbr": "ok"}, "244920": {"naver": true, "eps": "ok", "bps": "ok", "per": "ok", "pbr": "ok"}, "206640": {"naver": true, "eps": "blank", "bps": "ok", "per": "blank", "pbr": "ok"}, "018310": {"naver": true, "eps": "ok", "bps": "ok", "per": "ok", "pbr": "ok"}, "044450": {"naver": true, "eps": "ok", "bps": "ok", "per": "ok", "pbr": "ok"}, "067390": {"naver": true, "eps": "blank", "bps": "mismatch(1103 vs 769.0)", "per": "no_naver", "pbr": "mismatch(0.5 vs 0.71)"}, "000480": {"naver": true, "eps": "mismatch(-227 vs -459.0)", "bps": "ok", "per": "ok_unverified", "pbr": "ok"}, "357880": {"naver": true, "eps": "blank", "bps": "ok", "per": "no_naver", "pbr": "ok"}, "088260": {"naver": true, "eps": "blank", "bps": "ok", "per": "blank", "pbr": "ok"}, "432320": {"naver": true, "eps": "blank", "bps": "mismatch(2591 vs 1772.0)", "per": "no_naver", "pbr": "mismatch(0.58 vs 0.85)"}, "040350": {"naver": true, "eps": "ok", "bps": "ok", "per": "ok_unverified", "pbr": "ok"}, "294570": {"naver": true, "eps": "blank", "bps": "ok", "per": "blank", "pbr": "ok"}, "036030": {"naver": true, "eps": "blank", "bps": "ok", "per": "blank", "pbr": "ok"}, "389020": {"naver": true, "eps": "blank", "bps": "ok", "per": "no_naver", "pbr": "ok"}, "241590": {"naver": true, "eps": "ok", "bps": "mismatch(8359 vs 7630.0)", "per": "ok_unverified", "pbr": "mismatch(0.44 vs 0.49)"}, "053300": {"naver": true, "eps": "ok", "bps": "ok", "per": "ok", "pbr": "ok"}, "136490": {"naver": true, "eps": "ok", "bps": "ok", "per": "ok", "pbr": "ok"}, "099440": {"naver": true, "eps": "blank", "bps": "ok", "per": "no_naver", "pbr": "ok"}, "030210": {"naver": true, "eps": "ok", "bps": "ok", "per": "ok", "pbr": "ok"}, "0015G0": {"naver": true, "eps": "blank", "bps": "blank", "per": "blank", "pbr": "blank"}, "054210": {"naver": true, "eps": "ok", "bps": "mismatch(12957 vs 11460.0)", "per": "ok", "pbr": "mismatch(0.68 vs 0.77)"}, "353810": {"naver": true, "eps": "ok", "bps": "ok", "per": "ok", "pbr": "ok"}, "033920": {"naver": true, "eps": "ok", "bps": "ok", "per": "ok", "pbr": "ok"}, "484810": {"naver": true, "eps": "blank", "bps": "ok", "per": "no_naver", "pbr": "ok"}, "394800": {"naver": true, "eps": "blank", "bps": "ok", "per": "no_naver", "pbr": "ok"}, "025000": {"naver": true, "eps": "ok", "bps": "ok", "per": "ok", "pbr": "ok"}, "051370": {"naver": true, "eps": "ok", "bps": "ok", "per": "ok", "pbr": "ok"}, "134380": {"naver": true, "eps": "blank", "bps": "mismatch(80084 vs 9085.0)", "per": "blank", "pbr": "mismatch(0.13 vs 1.11)"}, "009680": {"naver": true, "eps": "mismatch(1174 vs 918.0)", "bps": "ok", "per": "mismatch(8.64 vs 11.05)", "pbr": "ok"}, "255220": {"naver": true, "eps": "ok", "bps": "ok", "per": "ok_unverified", "pbr": "ok"}, "084990": {"naver": true, "eps": "mismatch(-6 vs -7.0)", "bps": "ok", "per": "ok_unverified", "pbr": "ok"}, "035510": {"naver": true, "eps": "ok", "bps": "ok", "per": "ok", "pbr": "ok"}, "003650": {"naver": true, "eps": "blank", "bps": "ok", "per": "blank", "pbr": "ok"}, "005710": {"naver": true, "eps": "ok", "bps": "ok", "per": "ok", "pbr": "ok"}, "461300": {"naver": true, "eps": "blank", "bps": "ok", "per": "blank", "pbr": "ok"}, "138610": {"naver": true, "eps": "blank", "bps": "ok", "per": "blank", "pbr": "ok"}, "068930": {"naver": true, "eps": "ok", "bps": "ok", "per": "ok", "pbr": "ok"}, "464080": {"naver": true, "eps": "blank", "bps": "ok", "per": "no_naver", "pbr": "ok"}, "451760": {"naver": true, "eps": "ok", "bps": "ok", "per": "ok_unverified", "pbr": "ok"}, "007160": {"naver": true, "eps": "ok", "bps": "ok", "per": "ok_unverified", "pbr": "ok"}, "115450": {"naver": true, "eps": "ok", "bps": "ok", "per": "ok_unverified", "pbr": "ok"}, "008490": {"naver": true, "eps": "ok", "bps": "ok", "per": "ok", "pbr": "ok"}, "199820": {"naver": true, "eps": "ok", "bps": "ok", "per": "ok", "pbr": "ok"}, "028100": {"naver": true, "eps": "ok", "bps": "ok", "per": "ok", "pbr": "ok"}, "338840": {"naver": true, "eps": "blank", "bps": "ok", "per": "no_naver", "pbr": "ok"}, "035150": {"naver": true, "eps": "ok", "bps": "ok", "per": "ok", "pbr": "ok"}, "226320": {"naver": true, "eps": "ok", "bps": "mismatch(17974 vs 22375.0)", "per": "ok", "pbr": "mismatch(0.54 vs 0.44)"}, "094820": {"naver": true, "eps": "ok", "bps": "ok", "per": "ok", "pbr": "ok"}, "012210": {"naver": true, "eps": "blank", "bps": "ok", "per": "blank", "pbr": "ok"}, "210980": {"naver": true, "eps": "ok", "bps": "ok", "per": "ok_unverified", "pbr": "ok"}, "092070": {"naver": true, "eps": "blank", "bps": "ok", "per": "blank", "pbr": "ok"}, "049630": {"naver": true, "eps": "mismatch(153 vs 880.0)", "bps": "mismatch(961 vs 4810.0)", "per": "mismatch(59.48 vs 10.34)", "pbr": "mismatch(9.47 vs 1.89)"}, "083310": {"naver": true, "eps": "ok", "bps": "ok", "per": "ok_unverified", "pbr": "ok"}, "053210": {"naver": true, "eps": "blank", "bps": "blank", "per": "blank", "pbr": "blank"}, "001790": {"naver": true, "eps": "ok", "bps": "ok", "per": "ok_unverified", "pbr": "ok"}, "053690": {"naver": true, "eps": "ok", "bps": "ok", "per": "ok", "pbr": "ok"}, "009470": {"naver": true, "eps": "ok", "bps": "ok", "per": "ok", "pbr": "ok"}, "004560": {"naver": true, "eps": "ok", "bps": "ok", "per": "ok", "pbr": "ok"}, "013890": {"naver": true, "eps": "ok", "bps": "ok", "per": "ok_unverified", "pbr": "ok"}, "494120": {"naver": true, "eps": "mismatch(-923 vs -1041.0)", "bps": "ok", "per": "ok_unverified", "pbr": "ok"}, "001630": {"naver": true, "eps": "ok", "bps": "ok", "per": "ok", "pbr": "ok"}, "003220": {"naver": true, "eps": "ok", "bps": "ok", "per": "ok_unverified", "pbr": "ok"}, "380540": {"naver": true, "eps": "mismatch(-486 vs -993.0)", "bps": "mismatch(424 vs 850.0)", "per": "ok_unverified", "pbr": "mismatch(19.93 vs 9.94)"}, "013120": {"naver": true, "eps": "ok", "bps": "ok", "per": "ok", "pbr": "ok"}, "088800": {"naver": true, "eps": "ok", "bps": "mismatch(1082 vs 855.0)", "per": "ok_unverified", "pbr": "mismatch(2.52 vs 3.19)"}, "039570": {"naver": true, "eps": "ok", "bps": "ok", "per": "ok", "pbr": "ok"}, "045390": {"naver": true, "eps": "ok", "bps": "ok", "per": "ok", "pbr": "ok"}, "270660": {"naver": true, "eps": "blank", "bps": "ok", "per": "no_naver", "pbr": "ok"}, "052330": {"naver": true, "eps": "ok", "bps": "ok", "per": "ok", "pbr": "ok"}, "339770": {"naver": true, "eps": "ok", "bps": "ok", "per": "ok", "pbr": "ok"}, "214180": {"naver": true, "eps": "ok", "bps": "ok", "per": "ok", "pbr": "ok"}, "457550": {"naver": true, "eps": "blank", "bps": "ok", "per": "blank", "pbr": "ok"}, "004980": {"naver": true, "eps": "ok", "bps": "ok", "per": "ok", "pbr": "ok"}, "095570": {"naver": true, "eps": "ok", "bps": "ok", "per": "ok", "pbr": "ok"}, "432720": {"naver": true, "eps": "blank", "bps": "ok", "per": "no_naver", "pbr": "ok"}, "119610": {"naver": true, "eps": "ok", "bps": "mismatch(13031 vs 12045.0)", "per": "ok", "pbr": "ok"}, "007860": {"naver": true, "eps": "ok", "bps": "ok", "per": "ok", "pbr": "ok"}, "122990": {"naver": true, "eps": "ok", "bps": "ok", "per": "ok_unverified", "pbr": "ok"}, "382800": {"naver": true, "eps": "ok", "bps": "ok", "per": "ok", "pbr": "ok"}, "001130": {"naver": true, "eps": "mismatch(-17310 vs -1731.0)", "bps": "mismatch(607889 vs 61288.0)", "per": "ok_unverified", "pbr": "mismatch(0.02 vs 0.19)"}, "304100": {"naver": true, "eps": "ok", "bps": "ok", "per": "ok_unverified", "pbr": "ok"}, "126600": {"naver": true, "eps": "blank", "bps": "mismatch(10011 vs 6697.0)", "per": "blank", "pbr": "mismatch(0.32 vs 0.47)"}, "034810": {"naver": true, "eps": "ok", "bps": "mismatch(20100 vs 22002.0)", "per": "ok_unverified", "pbr": "ok"}, "402490": {"naver": true, "eps": "ok", "bps": "ok", "per": "ok", "pbr": "ok"}, "064550": {"naver": true, "eps": "mismatch(-37 vs -226.0)", "bps": "mismatch(8941 vs 7960.0)", "per": "ok_unverified", "pbr": "mismatch(0.86 vs 0.96)"}, "054450": {"naver": true, "eps": "ok", "bps": "ok", "per": "ok_unverified", "pbr": "ok"}, "121440": {"naver": true, "eps": "ok", "bps": "ok", "per": "ok", "pbr": "ok"}, "117580": {"naver": true, "eps": "blank", "bps": "ok", "per": "blank", "pbr": "ok"}, "489500": {"naver": true, "eps": "ok", "bps": "ok", "per": "ok", "pbr": "ok"}}}